[{"aid": 68071854, "videos": 1, "tid": 126, "tname": "\u4eba\u529bVOCALOID", "copyright": 1, "pic": "http://i2.hdslb.com/bfs/archive/52431c875a27796cb1cf595a9f65e1b589c7b658.jpg", "title": "\u3010\u674e\u4e91\u9f99\u3011\u8bf4\u597d\u4e0d\u54ed", "pubdate": 1568710473, "ctime": 1568710473, "desc": "\u97f3\u6e90\uff1a\u66b4\u529b\u8d1d\n\u5236\u4f5c\uff1a\u591c\u96e8\u661f\u7e41y", "state": 0, "duration": 135, "mission_id": 11878, "rights": {"bp": 0, "elec": 0, "download": 0, "movie": 0, "pay": 0, "hd5": 1, "no_reprint": 1, "autoplay": 1, "ugc_pay": 0, "is_cooperation": 0, "ugc_pay_preview": 0, "no_background": 0, "arc_pay": 0, "pay_free_watch": 0}, "owner": {"mid": 39422678, "name": "\u591c\u96e8\u661f\u7e41y", "face": "https://i2.hdslb.com/bfs/face/c2a20ba6c8ee98c14012179be24f3d0d462df879.jpg"}, "stat": {"aid": 68071854, "view": 652639, "danmaku": 2796, "reply": 810, "favorite": 9628, "coin": 27277, "share": 5309, "now_rank": 0, "his_rank": 65, "like": 36817, "dislike": 0, "vt": 0, "vv": 652639}, "dynamic": "#\u4eba\u529bVOCALOID##\u9b3c\u755c\u8c03\u6559##\u674e\u4e91\u9f99#", "cid": 117989598, "dimension": {"width": 1920, "height": 1080, "rotate": 0}, "short_link_v2": "https://b23.tv/BV1HJ411w776", "bvid": "BV1HJ411w776", "season_type": 0, "is_ogv": false, "ogv_info": null, "enable_vt": 0, "ai_rcmd": null, "rcmd_reason": "\u660e\u660e\u662f\u9b3c\u755c\uff0c\u4e3a\u4ec0\u4e48\u6211\u5374\u770b\u54ed\u4e86\u2026\u2026"}, {"aid": 67605913, "videos": 1, "tid": 28, "tname": "\u539f\u521b\u97f3\u4e50", "copyright": 1, "pic": "http://i2.hdslb.com/bfs/archive/2c8ae75cccf237e905197915f7f69e6e8bbd6332.png", "title": "\u3010\u5fc3\u4e4b\u7ae0\u3011\u300a\u5fc3\u300b", "pubdate": 1568376024, "ctime": 1568376024, "desc": "*\u672c\u4f5c\u54c1\u5df2\u5728\u4e2d\u56fd\u7248\u6743\u4e2d\u5fc3\u7533\u8bf7\u6388\u6743\uff0c\u672a\u7ecf\u672c\u4eba\u5141\u8bb8\uff0c\u4e25\u7981\u64c5\u81ea\u7528\u4e8e\u4efb\u4f55\u5546\u4e1a\u6d3b\u52a8\uff0c\u62d2\u7edd\u76d7\u7528\uff01\r\n\r\n\u8f6f\u4ef6\uff1a\r\nCubase 10 Pro\r\n\u97f3\u6e90\uff1a\r\n\u597d\u83b1\u575e\u5927\u63d0\u7434\u72ec\u594f\u3001\u5c0f\u63d0\u7434\u72ec\u594f\u3001\u7ad6\u7434\u72ec\u594f\r\n\u597d\u83b1\u575e\u5408\u5531\u56e2(Choir)\r\nSymphony Series\u7ba1\u5f26\u6253\u51fb\u4e50\u5168\u5957\r\nDamage\u6253\u51fb\u4e50\r\nThe Grandeur\u94a2\u7434\r\n\n\u5176\u5b9e\u8fd9\u9996\u66f2\u5b50\u662f\u63cf\u5199up\u672c\u4eba\u5185\u5fc3\u7684\u6210\u957f\u8fc7\u7a0b\u7684QwQ\n\r\n\u6c42\u70b9\u8d5e\uff0c\u6c42\u786c\u5e01\u554a\u554a\u554a\uff01\uff01\uff01", "state": 0, "duration": 419, "rights": {"bp": 0, "elec": 0, "download": 0, "movie": 0, "pay": 0, "hd5": 1, "no_reprint": 1, "autoplay": 1, "ugc_pay": 0, "is_cooperation": 0, "ugc_pay_preview": 0, "no_background": 0, "arc_pay": 0, "pay_free_watch": 0}, "owner": {"mid": 16437668, "name": "\u964c\u7136MajorC", "face": "https://i2.hdslb.com/bfs/face/bf0f9473c7c6af69fd292eda83653efe0addd612.jpg"}, "stat": {"aid": 67605913, "view": 4496282, "danmaku": 56483, "reply": 21579, "favorite": 396126, "coin": 768944, "share": 44926, "now_rank": 0, "his_rank": 1, "like": 691589, "dislike": 0, "vt": 0, "vv": 4496282}, "dynamic": "", "cid": 117203001, "dimension": {"width": 1920, "height": 1080, "rotate": 0}, "short_link_v2": "https://b23.tv/BV1JJ411N7Xj", "up_from_v2": 2, "bvid": "BV1JJ411N7Xj", "season_type": 0, "is_ogv": false, "ogv_info": null, "enable_vt": 0, "ai_rcmd": null, "rcmd_reason": "\u5988\u5988\u95ee\u6211\u4e3a\u4ec0\u4e48\u8dea\u7740\u770b\u89c6\u9891"}, {"aid": 67591920, "videos": 1, "tid": 65, "tname": "\u7f51\u7edc\u6e38\u620f", "copyright": 1, "pic": "http://i2.hdslb.com/bfs/archive/66f1ad4319950a8de9ae011090a3248cdc8023de.jpg", "title": "\u4fe9\u8001\u5916\u5728\u4e2d\u56fd\u670d\u52a1\u5668\u91cc\u75af\u72c2\u98d9\u4e2d\u6587\uff01\u751a\u81f3\u8fd8\u4e92\u76f8\u6559\u5b66\uff1f", "pubdate": 1568368911, "ctime": 1568368911, "desc": "\u271a\u559c\u6b22\u770b\u7684\u8bdd\u8fd8\u8bf7\u591a\u591a\u3010\u6295\u5e01\u3011\u652f\u6301\u5440~\u271a\n\u6e38\u620f\u540d\uff1aVRChat\uff08\u53ef\u4ee5VR\uff09\n\u5730\u56fe\uff1a\u4e2d\u6587\u5427 Chinesebar\n\u591a\u8c22\u89c2\u770b\u3002\n\u271a\u5fae\u535a@\u4fe1\u5f92Shinja\u271a", "state": 0, "duration": 442, "rights": {"bp": 0, "elec": 0, "download": 0, "movie": 0, "pay": 0, "hd5": 0, "no_reprint": 1, "autoplay": 1, "ugc_pay": 0, "is_cooperation": 0, "ugc_pay_preview": 0, "no_background": 0, "arc_pay": 0, "pay_free_watch": 0}, "owner": {"mid": 798527, "name": "\u4fe1\u5f92Shinja", "face": "https://i2.hdslb.com/bfs/face/e2337abfdb57d2c6cf717c711a44cbd2e12dea5d.jpg"}, "stat": {"aid": 67591920, "view": 11585134, "danmaku": 58672, "reply": 10352, "favorite": 339622, "coin": 390046, "share": 230039, "now_rank": 0, "his_rank": 2, "like": 653978, "dislike": 0, "vt": 0, "vv": 11585134}, "dynamic": "\u201c\u4f60\uff0c\u4f60\u4f1a\u8bf4\u82f1\u6587\u5417\uff1f\u201d\n\u201c\u6211\uff0c\u6211\u4f1a\uff0c\u6211\u4f1a\u8bf4\u82f1\u6587\u3002\u201d\n\u4e24\u4e2a\u7f8e\u56fd\u4eba\u5982\u662f\u804a\u8d77\u4e86\u5929\u2014\u2014", "cid": 117172597, "dimension": {"width": 1920, "height": 1080, "rotate": 0}, "short_link_v2": "https://b23.tv/BV1PJ411N7Ca", "bvid": "BV1PJ411N7Ca", "season_type": 0, "is_ogv": false, "ogv_info": null, "enable_vt": 0, "ai_rcmd": null, "rcmd_reason": "\u770b\u5230\u6700\u540e\uff0c\u4e0d\u7b11\u51fa\u732a\u53eb\u7b97\u6211\u8f93"}, {"aid": 67439251, "videos": 1, "tid": 28, "tname": "\u539f\u521b\u97f3\u4e50", "copyright": 1, "pic": "http://i0.hdslb.com/bfs/archive/cc5acb22606dc2ca5a37661a1b05bdb2840b4519.jpg", "title": "\u3010\u67d0\u5e7b/\u8001\u756a\u8304\u3011\u6700\u5f3a\u8131\u53d1\u738b\uff08\u79c3\u7235\uff09", "pubdate": 1568347221, "ctime": 1568263006, "desc": "\u6c99\u96d5\u8bf4\u5531\uff0c\u795d\u5927\u5bb6\u8eab\u4f53\u5065\u5eb7\uff0c\u5934\u9876\u8302\u5bc6\u3002\n\u4f5c\u8bcd\uff1a\u67d0\u5e7b\uff0c\u8001\u756a\u8304\n\u7f16\u66f2\uff1aCJ\n\u6df7\u97f3\uff1aCB\nPV\uff1a\u67d0\u5e7b\uff0c\u8001\u756a\u8304\uff0c\u9e22\u5c3e\u5c0f\u5c9b\uff0c\u5f3a\u5c3c", "state": 0, "duration": 169, "mission_id": 11884, "rights": {"bp": 0, "elec": 0, "download": 0, "movie": 0, "pay": 0, "hd5": 0, "no_reprint": 1, "autoplay": 1, "ugc_pay": 0, "is_cooperation": 1, "ugc_pay_preview": 0, "no_background": 0, "arc_pay": 0, "pay_free_watch": 0}, "owner": {"mid": 546195, "name": "\u8001\u756a\u8304", "face": "http://i0.hdslb.com/bfs/face/bc5ca101313d4db223c395d64779e76eb3482d60.jpg"}, "stat": {"aid": 67439251, "view": 17610654, "danmaku": 54881, "reply": 14103, "favorite": 461439, "coin": 827799, "share": 141660, "now_rank": 0, "his_rank": 1, "like": 966321, "dislike": 0, "vt": 0, "vv": 17610654}, "dynamic": "\u4f60\u79c3\u4e86\u5417\uff0c\u6ca1\u79c3\u8fdb\u6765\u542c\u542c :p", "cid": 116931494, "dimension": {"width": 1920, "height": 1080, "rotate": 0}, "short_link_v2": "https://b23.tv/BV1tJ411P7Cr", "bvid": "BV1tJ411P7Cr", "season_type": 0, "is_ogv": false, "ogv_info": null, "enable_vt": 0, "ai_rcmd": null, "rcmd_reason": "\u8bf4\u5531\u754c\u5189\u5189\u5347\u8d77\u4e86\u4e24\u9897\u65b0\u661f"}, {"aid": 67817729, "videos": 1, "tid": 250, "tname": "\u51fa\u884c", "copyright": 1, "pic": "http://i0.hdslb.com/bfs/archive/23a6c948108f0bcdc488f516305545567620b773.jpg", "title": "\u5c0f\u4f19\u82b11200\u79df\u4e86\u4e00\u8f86\u8dd1\u8f66\uff0c\u7ec8\u4e8e\u77e5\u9053\u56fd\u5185\u4e3a\u4ec0\u4e48\u90fd\u4e0d\u559c\u6b22\u5f00\u655e\u7bf7\u8f66\u4e86", "pubdate": 1568539846, "ctime": 1568539848, "desc": "\u5c0f\u7fd4\u54e5\u82b1\u4e861200\u79df\u4e86\u4e00\u8f86\u9ad8\u7ea7\u8dd1\u8f66\uff0c\u5f00\u7740\u655e\u7bf7\u73af\u6d31\u6d77\u4e00\u5708\u7279\u522b\u723d", "state": 0, "duration": 456, "rights": {"bp": 0, "elec": 0, "download": 0, "movie": 0, "pay": 0, "hd5": 0, "no_reprint": 1, "autoplay": 1, "ugc_pay": 0, "is_cooperation": 0, "ugc_pay_preview": 0, "no_background": 0, "arc_pay": 0, "pay_free_watch": 0}, "owner": {"mid": 196356191, "name": "\u7fd4\u7fd4\u5927\u4f5c\u6218", "face": "https://i2.hdslb.com/bfs/face/e78a0ec3ae75e953948677062f034eb93c7302d5.jpg"}, "stat": {"aid": 67817729, "view": 5337911, "danmaku": 26897, "reply": 6478, "favorite": 27694, "coin": 139637, "share": 9547, "now_rank": 0, "his_rank": 4, "like": 230112, "dislike": 0, "vt": 0, "vv": 5337911}, "dynamic": "\u8be5\u5b8c\u6210\u5b8c\u6210\u54b1\u4eec\u5927\u4eba\u7684\u68a6\u60f3\u4e86\u5427\u3002\n\n#\u655e\u7bf7\u8f66#", "cid": 117551768, "dimension": {"width": 1920, "height": 1080, "rotate": 0}, "short_link_v2": "https://b23.tv/BV1eJ411A7os", "bvid": "BV1eJ411A7os", "season_type": 0, "is_ogv": false, "ogv_info": null, "enable_vt": 0, "ai_rcmd": null, "rcmd_reason": "\u5c0f\u7fd4\u54e5\uff0c\u5f00\u655e\u7bf7\u8f66\u8981\u6d82\u597d\u9632\u6652"}, {"aid": 67879727, "videos": 1, "tid": 138, "tname": "\u641e\u7b11", "copyright": 1, "pic": "http://i0.hdslb.com/bfs/archive/0b4a75f7e55b545d33f39fab49cf43c67c27292a.jpg", "title": "\u5341\u65a4\u82b1\u7532\u4e00\u53e3\u6c14\u5168\u5403\u6389\uff01\u91cc\u9762\u7684\u8089\u4f30\u8ba1\u5c31\u4e00\u70b9\u585e\u7259\u7f1d\u90fd\u4e0d\u591f\uff01", "pubdate": 1568550592, "ctime": 1568550592, "desc": "youtube\u9891\u9053\uff1a\u656c\u6c49\u537f\u3010\u5b98\u65b9\u9891\u9053\u3011\n\u521b\u610f\u6295\u7a3f\u90ae\u7bb11905387728@qq.com\n\u6dd8\u5b9d\u5e97\uff1a\u656c\u6c49\u537f", "state": 0, "duration": 249, "rights": {"bp": 0, "elec": 0, "download": 0, "movie": 0, "pay": 0, "hd5": 0, "no_reprint": 1, "autoplay": 1, "ugc_pay": 0, "is_cooperation": 0, "ugc_pay_preview": 0, "no_background": 0, "arc_pay": 0, "pay_free_watch": 0}, "owner": {"mid": 9824766, "name": "\u656c\u6c49\u537f", "face": "https://i0.hdslb.com/bfs/face/fd8d7ad17af295f7c4256959705f009c5f67e9c6.jpg"}, "stat": {"aid": 67879727, "view": 7297816, "danmaku": 21051, "reply": 5450, "favorite": 21883, "coin": 109038, "share": 5006, "now_rank": 0, "his_rank": 4, "like": 287640, "dislike": 0, "vt": 0, "vv": 7297816}, "dynamic": "\u8fd9\u4e2a\u6311\u6218\u6211\u89c9\u5f97\u8c01\u90fd\u53ef\u4ee5\u505a\uff01\u53ea\u4e0d\u8fc7\u5403\u5230\u540e\u9762\u8d8a\u5403\u8d8a\u96be\u5403\n#\u4f5c\u6b7b##\u656c\u6c49\u537f##\u5e7d\u9ed8#", "cid": 117653323, "dimension": {"width": 1920, "height": 1080, "rotate": 0}, "short_link_v2": "https://b23.tv/BV19J411A7pF", "bvid": "BV19J411A7pF", "season_type": 0, "is_ogv": false, "ogv_info": null, "enable_vt": 0, "ai_rcmd": null, "rcmd_reason": "\u5403\u82b1\u7532\u4e00\u65f6\u723d\uff0c\u4e00\u76f4\u5403\u4e00\u76f4\u723d"}, {"aid": 67530671, "videos": 2, "tid": 22, "tname": "\u9b3c\u755c\u8c03\u6559", "copyright": 1, "pic": "http://i0.hdslb.com/bfs/archive/c5062f721dc160db18623ad79337bc8a340bd48b.jpg", "title": "\u3010\u5362\u672c\u4f1f\u4e3b\u6f14\u3011\u5934\u53f7\u73a9\u5bb6\uff01\u7b2c\u4e8c\u96c6\uff1a\u5362\u672c\u4f1f\u8eab\u9677\u4e5d\u4e5d\u516b\u5341\u4e00\u96be\uff0c\u80fd\u5426\u901a\u5173\uff1f", "pubdate": 1568347221, "ctime": 1568334465, "desc": "\u524d\u4f5cav57798444\n\u6bd5\u7adf\u662f\u5934\u53f7\u73a9\u5bb6\uff0c\u80af\u5b9a\u662f\u9700\u8981\u7528\u6e38\u620f\u6765\u505a\u7684\n\u540e\u9762\u7684\u6e38\u620f\u5927\u90e8\u5206\u662f\u4e00\u4e9b\u6211\u73a9\u8fc7\u7684\u6e38\u620f\u7684CG\u6216\u8005\u5f55\u5c4f\uff0c\u6240\u4ee5\u80fd\u505a\u8fdb\u89c6\u9891\u91cc\u611f\u89c9\u771f\u7684\u5f88\u4e0d\u9519\n\u8fd8\u6709\u5173\u4e8e\u4e4b\u524d\u9884\u544a\u7684\u4e00\u4e9b\u7247\u6bb5\u662f\u88ab\u6211\u5220\u51cf\u8fc7\u4e86\uff0c\u56e0\u4e3a\u611f\u89c9\u6548\u679c\u4e0d\u592a\u597d\u6bd4\u8f83\u62d6\u8282\u594f\n\u5bf9\u4e86\uff0c\u8fd8\u662f\u90a3\u53e5\u8bdd\uff0c\u5e0c\u671b\u628a\u5f00\u6302\u8fd9\u4e2a\u5f53\u6210\u4e00\u4e2a\u6897\uff0c\u6bd5\u7adf\u8fd9\u91cc\u662f\u9b3c\u755c\u533a\u561b\n\u8bb0\u5f97\u7d20\u8d28\u4e09\u8fde\u54c8\nBGM\nOne Way Or Another\nStayin' Alive\nPrisoner's Awakening\nSpecial Ops\nGreat Days\nScattered Remains", "state": 0, "duration": 822, "rights": {"bp": 0, "elec": 0, "download": 0, "movie": 0, "pay": 0, "hd5": 1, "no_reprint": 1, "autoplay": 1, "ugc_pay": 0, "is_cooperation": 0, "ugc_pay_preview": 0, "no_background": 0, "arc_pay": 0, "pay_free_watch": 0}, "owner": {"mid": 59905809, "name": "\u54e6\u547cw", "face": "https://i0.hdslb.com/bfs/face/57ead5621801ec8a637bc47754e00e9ae6e62888.gif"}, "stat": {"aid": 67530671, "view": 5781616, "danmaku": 34641, "reply": 5833, "favorite": 199060, "coin": 491262, "share": 60329, "now_rank": 0, "his_rank": 2, "like": 427845, "dislike": 0, "vt": 0, "vv": 5781616}, "dynamic": "\u4e2d\u79cb\u8282\u5feb\u4e50\uff01\n\u9b3c\u77e5\u9053\u6211\u770b\u4e86\u591a\u5c11\u7d20\u6750\uff0c\u8fd9\u6b21\u662f\u505a\u7684\u6700\u7d2f\u7684\u4e00\u6b21\u4e86\uff0c\u770b\u5b8c\u8bb0\u5f97\u4e09\u8fde\u54c8\n#\u5934\u53f7\u73a9\u5bb6##\u9b3c\u755c\u8c03\u6559##\u641e\u7b11#", "cid": 117092937, "dimension": {"width": 1920, "height": 1080, "rotate": 0}, "short_link_v2": "https://b23.tv/BV11J411P7Y9", "bvid": "BV11J411P7Y9", "season_type": 0, "is_ogv": false, "ogv_info": null, "enable_vt": 0, "ai_rcmd": null, "rcmd_reason": "\u6784\u601d\u7cbe\u5de7\uff0c\u6280\u672f\u5168\u9762\uff0cUP\u5b9e\u4e43\u7956\u56fd\u680b\u6881"}, {"aid": 68079639, "videos": 1, "tid": 138, "tname": "\u641e\u7b11", "copyright": 1, "pic": "http://i1.hdslb.com/bfs/archive/b775e385687929da8e0d128365126ae6432c848d.jpg", "title": "\u3010\u6731\u4e00\u65e6\u301169 \u505a\u4eba\u4e0d\u8981\u592a\u6500\u6bd4 \uff01", "pubdate": 1568716183, "ctime": 1568716183, "desc": "\u5fae\u535a\uff1a\u6731\u4e00\u65e6\u7684\u67af\u71e5\u751f\u6d3b\nYouTube\uff1a\u3010\u6731\u4e00\u65e6\u7684\u67af\u71e5\u751f\u6d3b\u3011\u5b98\u65b9\u9891\u9053", "state": 0, "duration": 61, "rights": {"bp": 0, "elec": 0, "download": 0, "movie": 0, "pay": 0, "hd5": 1, "no_reprint": 1, "autoplay": 1, "ugc_pay": 0, "is_cooperation": 0, "ugc_pay_preview": 0, "no_background": 0, "arc_pay": 0, "pay_free_watch": 0}, "owner": {"mid": 437316738, "name": "\u6731\u4e00\u65e6\u7684\u67af\u71e5\u751f\u6d3b", "face": "http://i0.hdslb.com/bfs/face/48ad92f9e0eb9516f491ed18457e2a73e865ea8c.jpg"}, "stat": {"aid": 68079639, "view": 6986133, "danmaku": 2213, "reply": 3331, "favorite": 20028, "coin": 101486, "share": 10480, "now_rank": 0, "his_rank": 7, "like": 255404, "dislike": 0, "vt": 0, "vv": 6986133}, "dynamic": "#\u6731\u4e00\u65e6# #\u67af\u71e5# #\u9152\u8089\u670b\u53cb#", "cid": 118002363, "dimension": {"width": 1080, "height": 1920, "rotate": 0}, "short_link_v2": "https://b23.tv/BV1VJ411w7ow", "bvid": "BV1VJ411w7ow", "season_type": 0, "is_ogv": false, "ogv_info": null, "enable_vt": 0, "ai_rcmd": null, "rcmd_reason": "\u5426\u5219\u5c31\u628a\u4f60\u9001\u53bb\u975e\u6d32"}, {"aid": 67591869, "videos": 1, "tid": 138, "tname": "\u641e\u7b11", "copyright": 1, "pic": "http://i1.hdslb.com/bfs/archive/c3b5a4b3d50a3652404d3f7d7b6535771f8a47bb.jpg", "title": "\u90ed\u6770\u745e\u4ece\u7f8e\u56fd\u5e26\u6765\u4eba\u9020\u8089\uff01\u7f8e\u56fd\u9ed1\u79d1\u6280\u4eba\u9020\u8089\u8fd8\u6ca1\u4e94\u6bdb\u7d20\u8089\u597d\u5403\uff1f", "pubdate": 1568368937, "ctime": 1568368937, "desc": "youtube\u9891\u9053\uff1a\u656c\u6c49\u537f\u3010\u5b98\u65b9\u9891\u9053\u3011\n\u521b\u610f\u6295\u7a3f\u90ae\u7bb11905387728@qq.com\n\u6dd8\u5b9d\u5e97\uff1a\u656c\u6c49\u537f", "state": 0, "duration": 279, "rights": {"bp": 0, "elec": 0, "download": 0, "movie": 0, "pay": 0, "hd5": 0, "no_reprint": 1, "autoplay": 1, "ugc_pay": 0, "is_cooperation": 0, "ugc_pay_preview": 0, "no_background": 0, "arc_pay": 0, "pay_free_watch": 0}, "owner": {"mid": 9824766, "name": "\u656c\u6c49\u537f", "face": "https://i0.hdslb.com/bfs/face/fd8d7ad17af295f7c4256959705f009c5f67e9c6.jpg"}, "stat": {"aid": 67591869, "view": 5360317, "danmaku": 21739, "reply": 5431, "favorite": 22348, "coin": 71767, "share": 3490, "now_rank": 0, "his_rank": 8, "like": 252762, "dislike": 0, "vt": 0, "vv": 5360317}, "dynamic": "\u611f\u8c22\u90ed\u6770\u745e\u4ece\u7f8e\u56fd\u5e26\u6765\u7684\u9ed1\u79d1\u6280\u4eba\u9020\u8089\uff01\u6211\u628a\u8fd9\u4e2a\u6bd4\u771f\u8089\u8fd8\u8d35\u7684\u4eba\u9020\u8089\u8ddf\u4e94\u6bdb\u94b1\u7d20\u8089\u6bd4\u600e\u4e48\u6837\n#\u5947\u8469##\u656c\u6c49\u537f##\u5e7d\u9ed8#", "cid": 117186401, "dimension": {"width": 1920, "height": 1080, "rotate": 0}, "short_link_v2": "https://b23.tv/BV1PJ411N7yY", "bvid": "BV1PJ411N7yY", "season_type": 0, "is_ogv": false, "ogv_info": null, "enable_vt": 0, "ai_rcmd": null, "rcmd_reason": "\u4f60\u4eec\u4fe9\u7684\u914d\u5408\u597d\u9ed8\u5951\u54c8\u54c8\u54c8"}, {"aid": 67455292, "videos": 1, "tid": 17, "tname": "\u5355\u673a\u6e38\u620f", "copyright": 1, "pic": "http://i0.hdslb.com/bfs/archive/6389747f721e2d5b720d18e28da999d07a6233cb.jpg", "title": "\u3010\u6556\u5382\u957f\u30111989\u5e74\u70b8\u88c2\u7ea7\u6c99\u76d2\u6e38\u620f 30\u5e74\u524d\u7684\u65e0\u4eba\u6df1\u7a7a", "pubdate": 1568275179, "ctime": 1568275179, "desc": "\u4e2d\u79cb\u5feb\u4e50\u5c0f\u4f19\u4f34\u4eec ,\u5145\u7535\u6295\u5e01\u6536\u85cf\u6765\u7838\u6211\u5427", "state": 0, "duration": 630, "rights": {"bp": 0, "elec": 0, "download": 0, "movie": 0, "pay": 0, "hd5": 1, "no_reprint": 1, "autoplay": 1, "ugc_pay": 0, "is_cooperation": 0, "ugc_pay_preview": 0, "no_background": 0, "arc_pay": 0, "pay_free_watch": 0}, "owner": {"mid": 122879, "name": "\u6556\u5382\u957f", "face": "https://i2.hdslb.com/bfs/face/3368af39da3285bdb46ee719b896602028433932.jpg"}, "stat": {"aid": 67455292, "view": 4926664, "danmaku": 34914, "reply": 6863, "favorite": 87693, "coin": 313385, "share": 18170, "now_rank": 0, "his_rank": 1, "like": 307498, "dislike": 0, "vt": 0, "vv": 4926664}, "dynamic": "#\u6556\u5382\u957f#\u4e2d\u79cb\u7279\u522b\u89c6\u9891\u53d1\u5e03\uff011989\u5e74\u70b8\u88c2\u7ea7\u6c99\u76d2\u6e38\u620f\uff0130\u5e74\u524d\u5c31\u6709\u65e0\u4eba\u6df1\u7a7a~\uff01", "cid": 116960664, "dimension": {"width": 1920, "height": 1080, "rotate": 0}, "season_id": 2884, "short_link_v2": "https://b23.tv/BV1pJ411P7Sa", "bvid": "BV1pJ411P7Sa", "season_type": 0, "is_ogv": false, "ogv_info": null, "enable_vt": 0, "ai_rcmd": null, "rcmd_reason": "\u6556\u5382\u957f\u56de\u5f52\u5e26\u4f60\u73a9\u6e38\u620f\u5566\uff01"}, {"aid": 67457647, "videos": 2, "tid": 154, "tname": "\u821e\u8e48\u7efc\u5408", "copyright": 1, "pic": "http://i1.hdslb.com/bfs/archive/e2a356b34e28feda14dcea93fb429a2c302aa95d.jpg", "title": "\u8292\u79cd\uff0c\u4e00\u60f3\u5230\u4f60\u6211\u5c31\u2026\u2026", "pubdate": 1568276257, "ctime": 1568276258, "desc": "\u8fd9\u4e00\u6b21\uff0c\u6211\u7ec8\u4e8e\u62cd\u5230\u8377\u82b1\u4e86\uff0c\u590f\u5929\u5728\u8377\u82b1\u6c60\u8fb9\u62cd\u821e\u771f\u7684\u9700\u8981\u597d\u8fd0\u6c14\u5440\uff0c\u771f\u5e78\u8fd0\u3002\n\u8fd9\u6b21\u7684\u821e\u8e48\u662f\u8292\u79cd\uff0c\u4e5f\u662f\u7ed9\u5927\u5bb6\u7684\u4e2d\u79cb\u793c\u7269\uff0c\u5e0c\u671b\u5927\u5bb6\u770b\u5f97\u5f00\u5fc3\uff0c\u613f\u5927\u5bb6\u4e2d\u79cb\u5feb\u4e50\uff01\n\n\u97f3\u4e50\uff1a\u8292\u79cd\uff0c\u97f3\u9619\u8bd7\u542c\n\u7f16\u821e\uff1a\u767d\u5c0f\u767d\uff0cav66178139", "state": 0, "duration": 212, "rights": {"bp": 0, "elec": 0, "download": 0, "movie": 0, "pay": 0, "hd5": 1, "no_reprint": 1, "autoplay": 1, "ugc_pay": 0, "is_cooperation": 0, "ugc_pay_preview": 0, "no_background": 0, "arc_pay": 0, "pay_free_watch": 0}, "owner": {"mid": 8366990, "name": "-\u6b23\u5c0f\u840c-", "face": "https://i2.hdslb.com/bfs/face/60368b5e2850cc569328e8b562d90cb28ce5b2cd.jpg"}, "stat": {"aid": 67457647, "view": 25574927, "danmaku": 43463, "reply": 11550, "favorite": 258458, "coin": 254818, "share": 74932, "now_rank": 0, "his_rank": 2, "like": 498669, "dislike": 0, "vt": 0, "vv": 25574927}, "dynamic": "", "cid": 116963870, "dimension": {"width": 1920, "height": 1080, "rotate": 0}, "short_link_v2": "https://b23.tv/BV1sJ411P7CF", "pub_location": "\u6c5f\u82cf", "bvid": "BV1sJ411P7CF", "season_type": 0, "is_ogv": false, "ogv_info": null, "enable_vt": 0, "ai_rcmd": null, "rcmd_reason": "\u522b\u95ee\u4e86\uff0cawsl\u5c31\u662f\u597d\u770b\uff01\uff01\uff01"}, {"aid": 68180250, "videos": 1, "tid": 183, "tname": "\u5f71\u89c6\u526a\u8f91", "copyright": 1, "pic": "http://i1.hdslb.com/bfs/archive/35a0611d609c7e51131518e83298406d6f42829c.jpg", "title": "\u4ed6\u4eec \u6b7b\u5728\u4e86\u7956\u56fd\u80dc\u5229\u7684\u524d\u591c", "pubdate": 1568810965, "ctime": 1568810965, "desc": "\u94ed\u8bb0\u5386\u53f2\uff0c\u4e0d\u5fd8\u56fd\u803b\n\u5411\u90a3\u4e9b\u5012\u5728\u7956\u56fd\u80dc\u5229\u524d\u591c\u7684\u82f1\u96c4\u4eec\n\u81f4\u4ee5\u6700\u5d07\u9ad8\u7684\u656c\u610f", "state": 0, "duration": 285, "mission_id": 11878, "rights": {"bp": 0, "elec": 0, "download": 0, "movie": 0, "pay": 0, "hd5": 0, "no_reprint": 1, "autoplay": 1, "ugc_pay": 0, "is_cooperation": 0, "ugc_pay_preview": 0, "no_background": 0, "arc_pay": 0, "pay_free_watch": 0}, "owner": {"mid": 6711923, "name": "\u5669\u68a6Crazy", "face": "https://i2.hdslb.com/bfs/face/4de39a5036b3d5ed4da32b9efda59d035b7dedae.jpg"}, "stat": {"aid": 68180250, "view": 25755035, "danmaku": 206858, "reply": 21400, "favorite": 1097055, "coin": 1687411, "share": 178908, "now_rank": 0, "his_rank": 1, "like": 1809842, "dislike": 0, "vt": 0, "vv": 25755035}, "dynamic": "\u4ed6\u4eec \u6b7b\u5728\u4e86\n\u7956\u56fd\u80dc\u5229\u7684\u524d\u591c\n\n#\u4e2d\u56fd\u8fd1\u4ee3\u53f2#\n#\u56fd\u5e8670\u5468\u5e74##\u4e5d\u4e00\u516b#", "cid": 118175938, "dimension": {"width": 1280, "height": 720, "rotate": 0}, "short_link_v2": "https://b23.tv/BV1mJ411g733", "bvid": "BV1mJ411g733", "season_type": 0, "is_ogv": false, "ogv_info": null, "enable_vt": 0, "ai_rcmd": null, "rcmd_reason": "\u5148\u8f88\u4e4b\u65e0\u91cf\u9c9c\u8840\uff0c\u94f8\u5c31\u6211\u65e0\u91cf\u4e2d\u534e"}, {"aid": 67904809, "videos": 1, "tid": 21, "tname": "\u65e5\u5e38", "copyright": 1, "pic": "http://i1.hdslb.com/bfs/archive/b40638a3783b385f5fc1ac577b8462c8535cb86d.jpg", "title": "\u3010\u8001\u756a\u8304\u3011\u6211\u6f5c\u5165\u8c37\u6b4c\u4e86\uff01", "pubdate": 1568635232, "ctime": 1568606100, "desc": "\u53c2\u52a0\u4e862019\u5e749\u670810-11\u65e5\u7684\u8c37\u6b4c\u5f00\u53d1\u8005\u5927\u4f1a\uff0c\u89c1\u5230\u4e86\u5f88\u591a\u65b0\u9c9c\u7684\u6280\u672f\uff01", "state": 0, "duration": 487, "order_id": 10010882, "rights": {"bp": 0, "elec": 0, "download": 0, "movie": 0, "pay": 0, "hd5": 0, "no_reprint": 1, "autoplay": 1, "ugc_pay": 0, "is_cooperation": 0, "ugc_pay_preview": 0, "no_background": 0, "arc_pay": 0, "pay_free_watch": 0}, "owner": {"mid": 546195, "name": "\u8001\u756a\u8304", "face": "http://i0.hdslb.com/bfs/face/bc5ca101313d4db223c395d64779e76eb3482d60.jpg"}, "stat": {"aid": 67904809, "view": 6969803, "danmaku": 37639, "reply": 6119, "favorite": 68993, "coin": 176672, "share": 9321, "now_rank": 0, "his_rank": 2, "like": 369317, "dislike": 0, "vt": 0, "vv": 6969803}, "dynamic": "#GOOGLE##\u8c37\u6b4c##\u751f\u6d3b#", "cid": 117861528, "dimension": {"width": 1920, "height": 1080, "rotate": 0}, "short_link_v2": "https://b23.tv/BV18J411c7KC", "bvid": "BV18J411c7KC", "season_type": 0, "is_ogv": false, "ogv_info": null, "enable_vt": 0, "ai_rcmd": null, "rcmd_reason": "\u9ed1\u79d1\u6280\u5927\u4f1a\uff0c\u606d\u559c\u8001\u756a\u8304\u89e3\u9501\u6210\u529f\uff01"}, {"aid": 67456873, "videos": 2, "tid": 20, "tname": "\u5b85\u821e", "copyright": 1, "pic": "http://i0.hdslb.com/bfs/archive/06ce21a3e9d69ff8bd65cba2f498316abc296f5b.jpg", "title": "\u3010\u54ac\u4eba\u732bX\u9732\u9732\u3011\u4eca\u5929\u4e0d\u4e0a\u73ed\uff01\u8df3\u731b\u7537\u7248\uff01\u65b0 \u5b9d \u5c9b\uff01", "pubdate": 1568289612, "ctime": 1568289623, "desc": "\u770b\u5230\u8fd9\u652f\u9b54\u6027\u7684\u821e\u5c31\u60f3\u8d77\u4ece\u524d\u548c\u9732\u9732\u5f55\u5c0f\u82f9\u679c\u65f6\u5019\u7684\u5feb\u4e50~\u4e0d\u4e00\u5b9a\u9700\u8981\u591a\u4e48\u6807\u51c6\u7684\u52a8\u4f5c\uff0c\u53ea\u8981\u4e00\u8d77\u73a9\u7684\u5f00\u5fc3\u5c31\u597d\u4e86\uff0c\u5e0c\u671b\u8fd9\u6b21\u5927\u5bb6\u4e5f\u80fd\u4f53\u9a8c\u5230\u4e00\u4efd\u548c\u5e73\u65f6\u821e\u8e48\u4e2d\u4e0d\u4e00\u6837\u7684\u6b22\u4e50\u3002\n\u9732\u9732\uff1a\u201c\u618b\u7b11\u592a\u96be\u4e86\uff0c\u618b\u7740\u626d\u8170\u8f6c\u5708\u592a\u96be\u4e86\uff0c\u8d81\u7740\u53ef\u4ee5\u653e\u8086\u7b11\u7684\u65f6\u5019\u522b\u8d70\u7a0b\u5e8f\uff0c\u76f4\u63a5\u7b11\u5427\u201d\n\u539f\u89c6\u9891\uff08\u52a0\u51cf\u4e58\u9664\u821e\uff09\uff1ahttps://www.youtube.com/watch?v=PJZb_127MLM\n\u53c2\u8003\u7248\u672c\uff1ahttps://twitter.com/MoriMorrix/status/1132639336552251393", "state": 0, "duration": 178, "rights": {"bp": 0, "elec": 0, "download": 0, "movie": 0, "pay": 0, "hd5": 1, "no_reprint": 1, "autoplay": 0, "ugc_pay": 0, "is_cooperation": 1, "ugc_pay_preview": 0, "no_background": 0, "arc_pay": 0, "pay_free_watch": 0}, "owner": {"mid": 116683, "name": "=\u54ac\u4eba\u732b=", "face": "http://i1.hdslb.com/bfs/face/8fad84a4470f3d894d8f0dc95555ab8f2cb10a83.jpg"}, "stat": {"aid": 67456873, "view": 25619590, "danmaku": 31795, "reply": 11507, "favorite": 281573, "coin": 285517, "share": 91320, "now_rank": 0, "his_rank": 3, "like": 479336, "dislike": 0, "vt": 0, "vv": 25619590}, "dynamic": "\u6211\u548c\u9732\u9732\u7684\u529e\u516c\u5ba4\u7248 \u65b0 \u5b9d \u5c9b\uff01P2\u8fd8\u6709\u9b54\u6027\u5012\u653e\u7248\u54df\uff01", "cid": 116938778, "dimension": {"width": 1920, "height": 1080, "rotate": 0}, "short_link_v2": "https://b23.tv/BV1pJ411P7zm", "pub_location": "\u56db\u5ddd", "bvid": "BV1pJ411P7zm", "season_type": 0, "is_ogv": false, "ogv_info": null, "enable_vt": 0, "ai_rcmd": null, "rcmd_reason": "\u4f17\u6240\u5468\u77e5\uff0cP2\u624d\u662f\u6b63\u7247"}, {"aid": 67720036, "videos": 1, "tid": 21, "tname": "\u65e5\u5e38", "copyright": 1, "pic": "http://i1.hdslb.com/bfs/archive/dc6e8ed0f26d3f52d677edeef741f9589aed7ec2.jpg", "title": "\u7206\u7b11\uff01\u7ea6\u4f1a\u4e00\u5929\u53ea\u80fd\u8bf4\u4e94\u53e5\u8bdd\u662f\u4ec0\u4e48\u6c99\u96d5\u4f53\u9a8c\uff1f", "pubdate": 1568452791, "ctime": 1568452791, "desc": "\u6211\u7b11\u6b7b\u4e86\uff0c\u4f60\u8981\u662f\u7b11\u4e86\u5c31\u70b9\u4e2a\u8d5e\u5457~", "state": 0, "duration": 510, "mission_id": 11878, "rights": {"bp": 0, "elec": 0, "download": 0, "movie": 0, "pay": 0, "hd5": 1, "no_reprint": 1, "autoplay": 1, "ugc_pay": 0, "is_cooperation": 0, "ugc_pay_preview": 0, "no_background": 0, "arc_pay": 0, "pay_free_watch": 0}, "owner": {"mid": 7552204, "name": "\u554a\u5417\u7cbd", "face": "https://i1.hdslb.com/bfs/face/61fc06811d9bb41a10a932b9f95ecc3632d82799.jpg"}, "stat": {"aid": 67720036, "view": 4118122, "danmaku": 29360, "reply": 4529, "favorite": 45293, "coin": 150971, "share": 57393, "now_rank": 0, "his_rank": 10, "like": 384574, "dislike": 0, "vt": 0, "vv": 4118122}, "dynamic": "\u4f60\u7b11\u6ca1\u7b11 \u7b11\u4e86\u5c31\u70b9\u4e2a\u8d5e\u5457\uff01", "cid": 117385291, "dimension": {"width": 1920, "height": 1080, "rotate": 0}, "short_link_v2": "https://b23.tv/BV1PJ411A7QX", "bvid": "BV1PJ411A7QX", "season_type": 0, "is_ogv": false, "ogv_info": null, "enable_vt": 0, "ai_rcmd": null, "rcmd_reason": "\u4eba\u7c7b\u7684\u672c\u8d28\u5c31\u662f\u590d\u8bfb\u673a"}, {"aid": 67749327, "videos": 1, "tid": 22, "tname": "\u9b3c\u755c\u8c03\u6559", "copyright": 1, "pic": "http://i1.hdslb.com/bfs/archive/60ba3d9afba328d77ceefae867f1d94d79587756.jpg", "title": "\u3010\u7231\u60c5\u516c\u5bd3rap\u3011\u5f20\u4f1f\uff1a\u4f60\u662f\u8f6f\u86cb \u4ed6\u662f\u6deb\u8d3c \u6211\u662f\u7a77\u9b3c", "pubdate": 1568512834, "ctime": 1568463775, "desc": "\u5230\u5e95\u8c01\u624d\u662f\u6700\u5f3a\u7684\u9a9a\u8bdd\u738b\u5462\uff1f\n\u770b\u7684\u8fa3\u4e48\u5f00\u5fc3\u4e0d\u8981\u5fd8\u8bb0\u4e09\u8fde+\u5173\u6ce8\u54e6~\nBGM\uff1aBang Bang - Dr. Dre\n\u7231\u60c5\u516c\u5bd3\u7cfb\u5217\u7b2c\u4e5d\u90e8\uff1aav84663924\n\u7231\u60c5\u516c\u5bd3\u7cfb\u5217\u7b2c\u4e03\u90e8\uff1aav77073377\n\u7231\u60c5\u516c\u5bd3\u7cfb\u5217\u7b2c\u516d\u90e8\uff1aav71310331\n\u7231\u60c5\u516c\u5bd3\u7cfb\u5217\u7b2c\u4e94\u90e8\uff1aav68369638\n\u7231\u60c5\u516c\u5bd3\u7cfb\u5217\u7b2c\u56db\u90e8\uff1a\uff08\u672c\u89c6\u9891\uff09\n\u7231\u60c5\u516c\u5bd3\u7cfb\u5217\u7b2c\u4e09\u90e8\uff1aav66259428\n\u7231\u60c5\u516c\u5bd3\u7cfb\u5217\u7b2c\u4e8c\u90e8\uff1aav62135098\n\u7231\u60c5\u516c\u5bd3\u7cfb\u5217\u7b2c\u4e00\u90e8\uff1aav60573140", "state": 0, "duration": 117, "mission_id": 11878, "rights": {"bp": 0, "elec": 0, "download": 0, "movie": 0, "pay": 0, "hd5": 0, "no_reprint": 1, "autoplay": 1, "ugc_pay": 0, "is_cooperation": 0, "ugc_pay_preview": 0, "no_background": 0, "arc_pay": 0, "pay_free_watch": 0}, "owner": {"mid": 250648682, "name": "\u7ea2\u8c46\u7a00\u996d\u4e2d", "face": "https://i2.hdslb.com/bfs/face/3dc6737d4ab6e8d0390409af88e9d24c3056a53b.jpg"}, "stat": {"aid": 67749327, "view": 18236848, "danmaku": 23434, "reply": 3253, "favorite": 416320, "coin": 552360, "share": 74661, "now_rank": 0, "his_rank": 7, "like": 1097570, "dislike": 0, "vt": 0, "vv": 18236848}, "dynamic": "#\u7231\u60c5\u516c\u5bd3##\u9b3c\u755c\u8c03\u6559##\u5f20\u4f1f#", "cid": 117440006, "dimension": {"width": 1920, "height": 1080, "rotate": 0}, "season_id": 8575, "short_link_v2": "https://b23.tv/BV1GJ411A7Xm", "bvid": "BV1GJ411A7Xm", "season_type": 0, "is_ogv": false, "ogv_info": null, "enable_vt": 0, "ai_rcmd": null, "rcmd_reason": "\u5168\u7a0b\u6838\u80fd\uff0c\u51fa\u4e0d\u53bb\u5566\uff01"}, {"aid": 68009422, "videos": 1, "tid": 251, "tname": "\u4e09\u519c", "copyright": 1, "pic": "http://i1.hdslb.com/bfs/archive/ebfb6fd495c1d6599b22c0ffc40d0b0c172fd659.jpg", "title": "\u534e\u519c\u5144\u5f1f\uff1a\u5c71\u4e0a\u7684\u5357\u9178\u67a3\u7ed3\u4e86\u597d\u591a\uff0c\u6211\u4eec\u53bb\u6361\u4e00\u70b9\u6765\u5403", "pubdate": 1568777439, "ctime": 1568726652, "desc": "\u534e\u519c\u5144\u5f1f\uff1a\u5c71\u4e0a\u7684\u5357\u9178\u67a3\u7ed3\u4e86\u597d\u591a\uff0c\u6211\u4eec\u53bb\u6361\u4e00\u70b9\u6765\u5403", "state": 0, "duration": 295, "rights": {"bp": 0, "elec": 0, "download": 0, "movie": 0, "pay": 0, "hd5": 0, "no_reprint": 1, "autoplay": 1, "ugc_pay": 0, "is_cooperation": 0, "ugc_pay_preview": 0, "no_background": 0, "arc_pay": 0, "pay_free_watch": 0}, "owner": {"mid": 250858633, "name": "\u534e\u519c\u5144\u5f1f", "face": "https://i1.hdslb.com/bfs/face/bac504655c69ab937b0be4557e27535f794b0c66.jpg"}, "stat": {"aid": 68009422, "view": 2665852, "danmaku": 16895, "reply": 4004, "favorite": 4189, "coin": 24219, "share": 2165, "now_rank": 0, "his_rank": 8, "like": 104873, "dislike": 0, "vt": 0, "vv": 2665852}, "dynamic": "\u534e\u519c\u5144\u5f1f\uff1a\u5c71\u4e0a\u7684\u5357\u9178\u67a3\u7ed3\u4e86\u597d\u591a\uff0c\u6211\u4eec\u53bb\u6361\u4e00\u70b9\u6765\u5403", "cid": 117876809, "dimension": {"width": 1920, "height": 1080, "rotate": 0}, "short_link_v2": "https://b23.tv/BV1FJ411w7XT", "bvid": "BV1FJ411w7XT", "season_type": 0, "is_ogv": false, "ogv_info": null, "enable_vt": 0, "ai_rcmd": null, "rcmd_reason": "\u5403\u4e0d\u4e86\u7684\u5c31\u515c\u7740\u8d70\uff01"}, {"aid": 68153467, "videos": 1, "tid": 21, "tname": "\u65e5\u5e38", "copyright": 1, "pic": "http://i1.hdslb.com/bfs/archive/f24205a59b145c874bd4bd83368a7f14aeeb84ee.jpg", "title": "\u8fd9\u4e0b\u73a9\u5d29\u4e86\u5427\uff01\u4e2d\u56fd\u5c0f\u4f19\u5728\u5bb6\u5077\u5077\u7528vr\u770b\u7247\uff0c\u88ab\u65e5\u672c\u5973\u53cb\u53d1\u73b0\u540e...\u300ekei\u548cmarin\u300f", "pubdate": 1568800859, "ctime": 1568800873, "desc": "up\u4e3b\u63a8\u8350 \u2605\u2605\u2605\u2605\u2605\u2605\u2605\u2605\u2605\u2605\u2605\u2605\u2605\u2605\u2605\u2605\u2605\u2605   \n\n\u95ee\u5b8c\u4f30\u8ba1\u8981\u5206\u624b\uff1aav67281091\n\u7ed9\u65e5\u672c\u5916\u5a46\u5c1d\u8bd5\u4e2d\u56fd\u7279\u4ea7\uff1aav66621433 \n\u6211\u5f53\u7238\u7238\u5566\uff1aav65477669  \n\u5077\u4e70\u7684\u5c0f\u25cb\u4e66\u88ab\u5973\u53cb\u53d1\u73b0\u4e86\uff1aav62649117  \n\u62cd\u89c6\u9891\u6211\u4eec\u4e00\u5171\u8d5a\u4e86\u591a\u5c11\u94b1\uff1aav58362965  \n\u6709\u94b1\u4eba\u8fd9\u4e48\u64a9\u59b9\uff1aav52848210", "state": 0, "duration": 265, "mission_id": 11934, "rights": {"bp": 0, "elec": 0, "download": 0, "movie": 0, "pay": 0, "hd5": 0, "no_reprint": 1, "autoplay": 1, "ugc_pay": 0, "is_cooperation": 0, "ugc_pay_preview": 0, "no_background": 0, "arc_pay": 0, "pay_free_watch": 0}, "owner": {"mid": 16853896, "name": "kei\u548cmarin", "face": "https://i1.hdslb.com/bfs/face/ec3456e625a0c9ab7064264e927e85fa05dfe9bd.jpg"}, "stat": {"aid": 68153467, "view": 6825413, "danmaku": 12841, "reply": 2457, "favorite": 28803, "coin": 69420, "share": 8605, "now_rank": 0, "his_rank": 6, "like": 230658, "dislike": 0, "vt": 0, "vv": 6825413}, "dynamic": "\u7b54\u5e94\u4f60\u4eec\u7684\u89c6\u9891\u603b\u7ec8\u4e8e\u6765\u4e86\uff01\u770b\u5230\u6700\u540e\u6211\u7684\u4e0b\u573a..\u6c423\u8fde\u5b89\u6170\u554a\uff01", "cid": 118127911, "dimension": {"width": 1920, "height": 1080, "rotate": 0}, "season_id": 746425, "short_link_v2": "https://b23.tv/BV1iJ411w7D4", "bvid": "BV1iJ411w7D4", "season_type": 0, "is_ogv": false, "ogv_info": null, "enable_vt": 0, "ai_rcmd": null, "rcmd_reason": "UP\u4e3b\u7684\u6c42\u751f\u6b32\u90fd\u4e0d\u89c1\u4e86"}]