[{"aid": 795637027, "videos": 1, "tid": 193, "tname": "MV", "copyright": 1, "pic": "http://i0.hdslb.com/bfs/archive/71dd7e2d957cc489b0ebb699f765d5c7e438ceea.jpg", "title": "\u300a\u5165\u6d77\u300bbilibili X \u6bdb\u4e0d\u6613 | \u8dc3\u5165\u4eba\u6d77\uff0c\u5404\u6709\u98ce\u96e8\u707f\u70c2", "pubdate": 1589934633, "ctime": 1589798118, "desc": "#\u5165\u6d77\u4e8c\u521b#\u540c\u6b65\u5f00\u542f\uff1ahttps://www.bilibili.com/blackboard/topic/activity-2020ruhai.html\n\u201c\u6bd5\u4e1a\u201d\u662f\u4e00\u4e2a\u7b26\u53f7\uff0c\u8c61\u5f81\u7740\u4e00\u4e2a\u4eba\u72ec\u7acb\u9762\u5bf9\u7740\u793e\u4f1a\u3001\u4eba\u751f\u548c\u672a\u6765\u3002\u6bcf\u4e2a\u4eba\u90fd\u4f1a\u7ecf\u5386\u8fd9\u4e00\u523b\uff0c\u8fd9\u662f\u6211\u4eec\u5171\u901a\u7684\u90e8\u5206\u3002B\u7ad9\u8054\u5408\u6bdb\u4e0d\u6613\u53d1\u5e03\u300a\u5165\u6d77\u300b\uff0c\u732e\u7ed9\u5373\u5c06\u6216\u5df2\u7ecf\u6bd5\u4e1a\u7684\u4eba\u4eec\uff0c\u8dc3\u5165\u4eba\u6d77\uff0c\u5404\u6709\u98ce\u96e8\u707f\u70c2\u3002\n\u5bfc\u6f14\uff1a\u5f20\u5927\u9e4f \u4e3b\u6f14\uff1a\u4f55\u5ed6\u4fa3\u5300 \u51b5\u742a\u513f \u6444\u5f71\u6307\u5bfc\uff1a\u51af\u4f70\u94a6 \u706f\u5149\u5e08\uff1a\u5434\u9704\u9f99 \u526a\u8f91\uff1a\u8463\u5317@\u8c1c\u4e00\u6837\u7684\u526a\u8f91\u5e08 \u5236\u7247\u4e3b\u4efb\uff1a\u9f50\u626c \u7f8e\u672f\uff1a\u9ec4\u535a \u670d\u88c5\u9020\u578b\uff1a\u5b59\u83b9 \u526f\u5bfc\u6f14\uff1a\u5f20\u5e06", "state": 0, "duration": 341, "rights": {"bp": 0, "elec": 0, "download": 0, "movie": 0, "pay": 0, "hd5": 1, "no_reprint": 1, "autoplay": 1, "ugc_pay": 0, "is_cooperation": 1, "ugc_pay_preview": 0, "no_background": 0, "arc_pay": 0, "pay_free_watch": 0}, "owner": {"mid": 8047632, "name": "\u54d4\u54e9\u54d4\u54e9\u5f39\u5e55\u7f51", "face": "https://i0.hdslb.com/bfs/face/0c84b9f4ad546d3f20324809d45fc439a2a8ddab.jpg"}, "stat": {"aid": 795637027, "view": 16938113, "danmaku": 79284, "reply": 41810, "favorite": 436047, "coin": 722462, "share": 322278, "now_rank": 0, "his_rank": 1, "like": 900157, "dislike": 0, "vt": 0, "vv": 16938113}, "dynamic": "#\u5165\u6d77#\u201c\u6bd5\u4e1a\u201d\u5176\u5b9e\u662f\u4e00\u4e2a\u7b26\u53f7\uff0c\u8c61\u5f81\u7740\u4e00\u4e2a\u4eba\u72ec\u7acb\u9762\u5bf9\u7740\u793e\u4f1a\u3001\u4eba\u751f\u548c\u672a\u6765\u3002\u6bcf\u4e2a\u4eba\u90fd\u4f1a\u7ecf\u5386\u8fd9\u4e00\u523b\uff0c\u8fd9\u662f\u6211\u4eec\u5171\u901a\u7684\u90e8\u5206\u3002bilibili\u00d7\u6bdb\u4e0d\u6613\u8054\u5408\u53d1\u5e03\u300a\u5165\u6d77\u300b\uff0c\u5e0c\u671b\u8fd9\u9996\u6b4c\u80fd\u591f\u6e29\u6696\u6211\u4eec\u5173\u4e8e\u6bd5\u4e1a\u7684\u8bb0\u5fc6\u3002\u613f\u5373\u5c06\u6216\u5df2\u7ecf\u6bd5\u4e1a\u7684\u4eba\u4eec\uff0c\u8dc3\u5165\u4eba\u6d77\uff0c\u5404\u6709\u98ce\u96e8\u707f\u70c2\u3002\u7ad9\u5185\u6709\u5956\u4e8c\u521b\u540c\u6b65\u5f00\u542f\uff0c\u8be6\u60c5\u8bf7\u6233\uff1ahttps://www.bilibili.com/blackboard/topic/activity-2020ruhai.html", "cid": 192966399, "dimension": {"width": 1920, "height": 1080, "rotate": 0}, "short_link_v2": "https://b23.tv/BV1tC4y1H7yz", "pub_location": "\u4e0a\u6d77", "bvid": "BV1tC4y1H7yz", "season_type": 0, "is_ogv": false, "ogv_info": null, "enable_vt": 0, "ai_rcmd": null, "rcmd_reason": "\u795d\u613f\u6240\u6709\u6bd5\u4e1a\u751f\u4eec\u524d\u7a0b\u4f3c\u9526\uff01"}, {"aid": 710727237, "videos": 1, "tid": 22, "tname": "\u9b3c\u755c\u8c03\u6559", "copyright": 1, "pic": "http://i1.hdslb.com/bfs/archive/49f714eb27937bbca5b14d8033eeb4f7838fb1b5.jpg", "title": "\u3010\u7279\u6717\u666e\u3011\u6ca1\u6709\u4eba\u6bd4\u6211\u66f4\u61c2\u6a21\u4eff\uff01", "pubdate": 1589536814, "ctime": 1589536814, "desc": "\u7279\u6717\u666e\u513f\u7ae5\u6a21\u4eff\u79c0\uff0c\u6296\u817f\u5c31\u5b8c\u4e8b\u4e86\nBGM\uff1aYung Bae - We Came to Boogie", "state": 0, "duration": 82, "rights": {"bp": 0, "elec": 0, "download": 0, "movie": 0, "pay": 0, "hd5": 1, "no_reprint": 1, "autoplay": 1, "ugc_pay": 0, "is_cooperation": 0, "ugc_pay_preview": 0, "no_background": 0, "arc_pay": 0, "pay_free_watch": 0}, "owner": {"mid": 515993, "name": "\u67aa\u5f39\u8f68\u8ff9", "face": "https://i2.hdslb.com/bfs/face/f47fae877fc26e3ada182b01a65c00dc006d0334.jpg"}, "stat": {"aid": 710727237, "view": 12510830, "danmaku": 18848, "reply": 6295, "favorite": 287212, "coin": 294591, "share": 91828, "now_rank": 0, "his_rank": 1, "like": 946741, "dislike": 0, "vt": 0, "vv": 12510830}, "dynamic": "#\u9b3c\u755c\u8c03\u6559##\u7279\u6717\u666e##\u7f8e\u56fd\u603b\u7edf#", "cid": 191354075, "dimension": {"width": 1920, "height": 1080, "rotate": 0}, "short_link_v2": "https://b23.tv/BV1zQ4y1A7qz", "bvid": "BV1zQ4y1A7qz", "season_type": 0, "is_ogv": false, "ogv_info": null, "enable_vt": 0, "ai_rcmd": null, "rcmd_reason": "\u5f00\u542f\u6d17\u8111\u5faa\u73af\u548c\u6296\u817f\u6a21\u5f0f"}, {"aid": 795634551, "videos": 1, "tid": 138, "tname": "\u641e\u7b11", "copyright": 1, "pic": "http://i0.hdslb.com/bfs/archive/1ec1d95f5cb61277dc760697a8719366bec77f04.jpg", "title": "\u82b1\u4e24\u767e\u4e07\u5a36\u7684\u8001\u5a46\u5230\u671f\u4e86\u3010\u9605\u7247\u65e0\u657048\u3011", "pubdate": 1589983230, "ctime": 1589958741, "desc": "\u60f3\u770b\u66f4\u591a\u7684\u9605\u7247\u65e0\u6570\u5c0f\u4f19\u4f34\u4eec\u8f6c\u53d1\u4e09\u8fde\u641e\u8d77\u6765\u54e6\n\u66f4\u591a\u751f\u6d3b\u4e2d\u7684\u51c9\u98ce\u8bf7\u53c2\u89c1\u2192\u5fae\u535a@\u51c9\u98ceKaze\n\u7b2c\u56db\u5341\u4e03\u671fBV1Bt4y117Bf\uff1a\u7edd\u4e86\uff01\u8fd9\u662f\u65e5\u672c\u62cd\u7684\u6297\u65e5\u795e\u5267\uff1f\n\u7b2c\u56db\u5341\u516d\u671fBV1Gt4y117MH\uff1a\u4f60\u7ba1\u8fd9\u53eb\u62a2\u94f6\u884c\uff1f\n\u7b2c\u56db\u5341\u4e94\u671fBV1rA41147BN\uff1a\u7adf\u7136\u6709\u4eba\u5728\u65b0\u95fb\u8054\u64ad\u91cc\u770b\u52a8\u753b\uff01\n\u7b2c\u56db\u5341\u56db\u671fBV1qa4y1x71d\uff1a\u542c\u542c\u8fd9\u662f\u4eba\u8bf4\u7684\u8bdd\uff1f\n\u7b2c\u56db\u5341\u4e09\u671fBV14t4y127yi\uff1a\u7537\u5b50\u56e0\u9020\u8c23\u81ea\u5df1\u88ab\u8b66\u65b9\u902e\u6355\u800c\u88ab\u8b66\u65b9\u902e\u6355", "state": 0, "duration": 851, "mission_id": 13400, "rights": {"bp": 0, "elec": 0, "download": 0, "movie": 0, "pay": 0, "hd5": 1, "no_reprint": 1, "autoplay": 1, "ugc_pay": 0, "is_cooperation": 0, "ugc_pay_preview": 0, "no_background": 0, "arc_pay": 0, "pay_free_watch": 0}, "owner": {"mid": 14110780, "name": "\u51c9\u98ceKaze", "face": "https://i1.hdslb.com/bfs/face/e0cc906bb531195e9ee9f3b575effdd2b056eaea.jpg"}, "stat": {"aid": 795634551, "view": 6683904, "danmaku": 77389, "reply": 13186, "favorite": 80102, "coin": 301593, "share": 16180, "now_rank": 0, "his_rank": 3, "like": 660578, "dislike": 0, "vt": 0, "vv": 6683904}, "dynamic": "520\u5230\u4e86\u5e0c\u671b\u4f60\u4eec\u90fd\u80fd\u62b1\u7740\u5bf9\u8c61\u770b#\u9605\u7247\u65e0\u6570#", "cid": 193153128, "dimension": {"width": 1920, "height": 1080, "rotate": 0}, "season_id": 175, "short_link_v2": "https://b23.tv/BV14C4y1H7n9", "bvid": "BV14C4y1H7n9", "season_type": 0, "is_ogv": false, "ogv_info": null, "enable_vt": 0, "ai_rcmd": null, "rcmd_reason": "\u81ea\u53e4\u8868\u767d\u591a\u767d\u8868\uff0c\u4e14\u770b\u51c9\u98ce\u7b11\u98ce\u51c9\u3002"}, {"aid": 540692691, "videos": 1, "tid": 22, "tname": "\u9b3c\u755c\u8c03\u6559", "copyright": 1, "pic": "http://i0.hdslb.com/bfs/archive/f1dd52536bc7f23fad5dbb9eae93fcd26d72b38b.png", "title": "\u6700 \u5f3a \u6cd5 \u6d77", "pubdate": 1589796036, "ctime": 1589776212, "desc": "?\u5927\u5a01\u5929\u9f99\uff01?\u5927\u7f57\u6cd5\u5492\uff01?\u822c\u82e5\u8bf8\u4f5b\uff01?\u5e08\u5c0a\u5730\u85cf\uff01\u270b\u822c\u82e5\u5df4\u9ebb\u54c4\uff01?\u98de\u9f99\u5728\u5929\uff01", "state": 0, "duration": 99, "mission_id": 13382, "rights": {"bp": 0, "elec": 0, "download": 0, "movie": 0, "pay": 0, "hd5": 0, "no_reprint": 1, "autoplay": 1, "ugc_pay": 0, "is_cooperation": 0, "ugc_pay_preview": 0, "no_background": 0, "arc_pay": 0, "pay_free_watch": 0}, "owner": {"mid": 96070394, "name": "\u63a8\u80cc\u5154\u306e", "face": "https://i2.hdslb.com/bfs/face/db356930131b40a4c457b29e393a1b1999fee477.jpg"}, "stat": {"aid": 540692691, "view": 63914111, "danmaku": 147490, "reply": 36242, "favorite": 1227393, "coin": 1377613, "share": 443187, "now_rank": 0, "his_rank": 2, "like": 2396644, "dislike": 0, "vt": 0, "vv": 63914111}, "dynamic": "#\u9b3c\u755c\u8c03\u6559##\u641e\u7b11##\u5927\u5a01\u5929\u9f99#\ud83e\udd18\u5927\u5a01\u5929\u9f99\uff01\ud83e\udd19\u5927\u7f57\u6cd5\u5492\uff01\ud83d\ude4f\u822c\u82e5\u8bf8\u4f5b\uff01\ud83d\udc4c\u5e08\u5c0a\u5730\u85cf\uff01\u270b\u822c\u82e5\u5df4\u9ebb\u54c4\uff01\ud83d\udc09\u98de\u9f99\u5728\u5929\uff01", "cid": 192377166, "dimension": {"width": 1280, "height": 720, "rotate": 0}, "season_id": 268637, "short_link_v2": "https://b23.tv/BV1pi4y147tQ", "pub_location": "\u8fbd\u5b81", "bvid": "BV1pi4y147tQ", "season_type": 0, "is_ogv": false, "ogv_info": null, "enable_vt": 0, "ai_rcmd": null, "rcmd_reason": "\u539f\u6765\u662f\u7535\u97f3\u5bfa\u6cd5\u6d77\u554a"}, {"aid": 925709117, "videos": 1, "tid": 24, "tname": "MAD\u00b7AMV", "copyright": 1, "pic": "http://i0.hdslb.com/bfs/archive/891ce95eb6e1eae2d0dd10359a0a81bf4931b870.jpg", "title": "\u201c\u8bf7\u95ee\uff0c\u4f60\u6709\u591a\u4e45\u6ca1\u6709\u559c\u6b22\u4e0a\u4e00\u4e2a\u5973\u5b69\u5b50\u4e86\uff1f\u201d", "pubdate": 1589878810, "ctime": 1589866534, "desc": "\u7b80\u4ecb\uff1a\n\u5728\u6b64\u6b21\u66f4\u65b0\uff1a\n1\uff1a\u589e\u5f3a\u7684\u89c6\u9891\u7684\u6e05\u6670\u5ea6\n2\uff1a\u7565\u5fae\u63d0\u9ad8\u4e86\u5e27\u7387\n3\uff1a\u589e\u5f3a\u4e86\u5206\u955c\n4\uff1a\u524a\u5f31\u4e86up\u4e3b\u7684\u5934\u53d1\n\u3010\u65b0\u589e\u3011\uff1aup\u7684\u71ac\u591c\u9ed1\u773c\u5708\n\u95ee\u9898\u4fee\u590d\uff1a\n1\uff1a\u4fee\u590d\u4e86\u4e3a\u4e86\u8e29\u70b9\u800c\u8e29\u70b9\u7684BUG\n2\uff1a\u4fee\u590d\u4e86up\u7684\u8e29\u70b9\u8282\u594f\u4e0d\u7a33\u7684\u95ee\u9898\n3\uff1a\u73b0\u5728\uff0cup\u53ef\u4ee5\u66f4\u52a0\u7075\u6d3b\u7684\u4f7f\u7528\u62c9\u955c\n\u603b\u7ed3\uff1a\n\u524a\u5f31\u4e86\u524d\u671f\u7684\u7a33\u5b9a\u8282\u594f\uff0c\u4f46\u653e\u6162\u8282\u594f\u540e\uff0c\u540e\u671f\u6210\u578b\u540e\u80fd\u529b\u6bd4\u4ee5\u5f80\u66f4\u9ad8\u4e86\uff08\u5c0f\u52a0\u5f3a\uff09\n\u63a5\u4e0b\u6765up\u7684mad\u4f5c\u54c1\uff0c\u6211\u4eec\u5c06\u4f1a\u7ee7\u7eed\u89c2\u671b\uff01\n\u672c\u6b21\u89c6\u9891\u8054\u52a8\uff1aBV1Wa4y1e71v  @\u662fSakura\u4e36\u6a31\u4e03\u4e03\n\u89c6\u9891\u7c7b\u578b\uff1aMAD\n\u7d20\u6750\uff1a\u8be6\u89c1\u8bc4\u8bba\nBGM\u3010\u97f3\u4e50\u540d\u3011Almost", "state": 0, "duration": 120, "mission_id": 13382, "rights": {"bp": 0, "elec": 0, "download": 0, "movie": 0, "pay": 0, "hd5": 0, "no_reprint": 1, "autoplay": 1, "ugc_pay": 0, "is_cooperation": 0, "ugc_pay_preview": 0, "no_background": 0, "arc_pay": 0, "pay_free_watch": 0}, "owner": {"mid": 30502823, "name": "\u5b66\u59d0\u5706", "face": "https://i2.hdslb.com/bfs/face/2e0e47571d612323fdd1991a01d5e4fefa4dd8ad.webp"}, "stat": {"aid": 925709117, "view": 1236565, "danmaku": 6661, "reply": 4127, "favorite": 44482, "coin": 39379, "share": 3594, "now_rank": 0, "his_rank": 0, "like": 80215, "dislike": 0, "vt": 0, "vv": 1236565}, "dynamic": "#MAD.AMV##\u8bbaBGM\u7684\u91cd\u8981\u6027##\u552f\u7f8e#\u554a\uff0c\u6211\u597d\u77ed~", "cid": 192755114, "dimension": {"width": 1920, "height": 1080, "rotate": 0}, "season_id": 26434, "short_link_v2": "https://b23.tv/BV1rT4y1u7iY", "bvid": "BV1rT4y1u7iY", "season_type": 0, "is_ogv": false, "ogv_info": null, "enable_vt": 0, "ai_rcmd": null, "rcmd_reason": "\u591a\u4e45\u6ca1\u5973\u5b69\u5b50\u559c\u6b22\u4e86(\u221a)"}, {"aid": 498216174, "videos": 1, "tid": 138, "tname": "\u641e\u7b11", "copyright": 1, "pic": "http://i0.hdslb.com/bfs/archive/a021c328da69bd7b55bfa80b0c7f34b73e3410ef.jpg", "title": "\u6559\u4f60\u4e00\u53e5\u8bdd\u628a\u5929\u804a\u6b7b\uff01", "pubdate": 1589636450, "ctime": 1589636450, "desc": "\u8fd9\u8fd8\u7528\u6559\uff1f", "state": 0, "duration": 98, "mission_id": 13382, "rights": {"bp": 0, "elec": 0, "download": 0, "movie": 0, "pay": 0, "hd5": 0, "no_reprint": 1, "autoplay": 1, "ugc_pay": 0, "is_cooperation": 0, "ugc_pay_preview": 0, "no_background": 0, "arc_pay": 0, "pay_free_watch": 0}, "owner": {"mid": 442177273, "name": "\u8ba1\u7b97\u673a\u5b66\u957f", "face": "https://i1.hdslb.com/bfs/face/973523eb7b400942bb0d9d94a4614e89bebad46c.jpg"}, "stat": {"aid": 498216174, "view": 6115259, "danmaku": 22875, "reply": 8167, "favorite": 170947, "coin": 93193, "share": 73319, "now_rank": 0, "his_rank": 8, "like": 526775, "dislike": 0, "vt": 0, "vv": 6115259}, "dynamic": "#\u641e\u7b11##\u5168\u80fd\u6253\u5361\u6311\u6218##\u5c2c\u804a#", "cid": 191782885, "dimension": {"width": 1920, "height": 1080, "rotate": 0}, "short_link_v2": "https://b23.tv/BV1RK411W78o", "bvid": "BV1RK411W78o", "season_type": 0, "is_ogv": false, "ogv_info": null, "enable_vt": 0, "ai_rcmd": null, "rcmd_reason": "\u6211\u5929\u751f\u5c31\u4f1a\u8fd9\u4e2a\u6280\u80fd [\u5927\u54ed]"}, {"aid": 413208908, "videos": 1, "tid": 17, "tname": "\u5355\u673a\u6e38\u620f", "copyright": 1, "pic": "http://i0.hdslb.com/bfs/archive/b31ec624091da4d1fc7fd6d94782ad3c995339bc.jpg", "title": "\u80fd\u4e0d\u80fd\u597d\u597d\u8d70\u8def\uff01\uff1f", "pubdate": 1589805528, "ctime": 1589805528, "desc": "\u73cd\u60dc\u53cc\u817f", "state": 0, "duration": 1214, "mission_id": 13415, "rights": {"bp": 0, "elec": 0, "download": 0, "movie": 0, "pay": 0, "hd5": 1, "no_reprint": 1, "autoplay": 1, "ugc_pay": 0, "is_cooperation": 0, "ugc_pay_preview": 0, "no_background": 0, "arc_pay": 0, "pay_free_watch": 0}, "owner": {"mid": 2206456, "name": "\u82b1\u5c11\u5317\u4e36", "face": "https://i1.hdslb.com/bfs/face/06c233a0136f738f8f54a08770dc7d484ae45081.jpg"}, "stat": {"aid": 413208908, "view": 4009449, "danmaku": 96515, "reply": 10979, "favorite": 61139, "coin": 177206, "share": 7705, "now_rank": 0, "his_rank": 1, "like": 295894, "dislike": 0, "vt": 0, "vv": 4009449}, "dynamic": "\u73a9\u5b8c\u8fd9\u6e38\u620f\u60f3\u51fa\u53bb\u8dd1\u4e00\u5708", "cid": 192519225, "dimension": {"width": 1920, "height": 1080, "rotate": 0}, "short_link_v2": "https://b23.tv/BV1MV411C7a7", "bvid": "BV1MV411C7a7", "season_type": 0, "is_ogv": false, "ogv_info": null, "enable_vt": 0, "ai_rcmd": null, "rcmd_reason": "\u9ad8\u8df7\u6a21\u62df\u5668\uff08\u00d7\uff09 \u62dc\u5e74\u6a21\u62df\u5668\uff08\u221a\uff09"}, {"aid": 968173197, "videos": 1, "tid": 85, "tname": "\u5c0f\u5267\u573a", "copyright": 1, "pic": "http://i1.hdslb.com/bfs/archive/99579ec77a08e125b8750b12ae896e31a95138f5.jpg", "title": "\u6211\u7ffb\u62cd\u4e86\u300a\u4e0a\u6d77\u5821\u5792\u300b\uff0c\u4e94\u6bdb\u94b1\u7279\u6548\u80fd\u5426\u6311\u62181.24\u4ebf\u7968\u623f\uff1f", "pubdate": 1589802171, "ctime": 1589802172, "desc": "\u547c\u547c\u3002\u3002\u3002\u7206\u809d\u597d\u51e0\u5929\u7ec8\u4e8e\u8d76\u5236\u51fa\u6765\u4e86\u3002\u7ed9\u4e2a\u4e09\u8fde\u5427\u8bf8\u4f4d\uff0c\u771f\u6ef4\u4e0d\u5bb9\u6613\uff0c\u62cd\u5b8c\u4e4b\u540e\u6211\u90fd\u7626\u4e86\uff0c\u5f00\u59cb\u5fc3\u75bc\u4e0a\u6d77\u5821\u5792\u7684\u5267\u7ec4\u4e86\u3002", "state": 0, "duration": 126, "mission_id": 13243, "rights": {"bp": 0, "elec": 0, "download": 0, "movie": 0, "pay": 0, "hd5": 0, "no_reprint": 1, "autoplay": 1, "ugc_pay": 0, "is_cooperation": 0, "ugc_pay_preview": 0, "no_background": 0, "arc_pay": 0, "pay_free_watch": 0}, "owner": {"mid": 297294750, "name": "\u753b\u7f3a", "face": "https://i0.hdslb.com/bfs/face/635eea10132c45fc2c85aa47fea6f999cab55468.jpg"}, "stat": {"aid": 968173197, "view": 5603605, "danmaku": 8585, "reply": 4366, "favorite": 56824, "coin": 88618, "share": 16658, "now_rank": 0, "his_rank": 12, "like": 422979, "dislike": 0, "vt": 0, "vv": 5603605}, "dynamic": "#bilibili\u65b0\u661f\u8ba1\u5212##\u9ad8\u80fd##\u7279\u6548#", "cid": 192531287, "dimension": {"width": 1280, "height": 720, "rotate": 0}, "season_id": 21141, "short_link_v2": "https://b23.tv/BV1vp4y1Q7fn", "bvid": "BV1vp4y1Q7fn", "season_type": 0, "is_ogv": false, "ogv_info": null, "enable_vt": 0, "ai_rcmd": null, "rcmd_reason": "\u53eb\u4f60\u6a21\u4eff\uff0c\u6ca1\u53eb\u4f60\u8d85\u8d8a\uff01"}, {"aid": 200731108, "videos": 1, "tid": 21, "tname": "\u65e5\u5e38", "copyright": 1, "pic": "http://i1.hdslb.com/bfs/archive/b5277fdfa8b729dec313eeaafc9fd97d94b02d5c.jpg", "title": "\u62ff\u59d0\u6000\u5b55\u4e86\uff1f\u6211\u771f\u7684\u614c\u4e86\uff01\uff01", "pubdate": 1589941844, "ctime": 1589941845, "desc": "\u611f\u8c22\u5927\u5bb6\u4e00\u76f4\u4ee5\u6765\u7684\u966a\u4f34\uff01\n\u7ee7\u7eed\u52aa\u529b\u5457\uff01\u6ca1\u5565~\n\u6c42\u5173\u6ce8\uff01\u6c42\u4e09\u8fde\uff01", "state": 0, "duration": 636, "mission_id": 13424, "rights": {"bp": 0, "elec": 0, "download": 0, "movie": 0, "pay": 0, "hd5": 1, "no_reprint": 1, "autoplay": 1, "ugc_pay": 0, "is_cooperation": 0, "ugc_pay_preview": 0, "no_background": 0, "arc_pay": 0, "pay_free_watch": 0}, "owner": {"mid": 7552204, "name": "\u554a\u5417\u7cbd", "face": "https://i1.hdslb.com/bfs/face/61fc06811d9bb41a10a932b9f95ecc3632d82799.jpg"}, "stat": {"aid": 200731108, "view": 13566927, "danmaku": 189924, "reply": 37403, "favorite": 259303, "coin": 1547580, "share": 40660, "now_rank": 0, "his_rank": 2, "like": 1376301, "dislike": 0, "vt": 0, "vv": 13566927}, "dynamic": "\u62ff\u59d0\u6000\u5b55\u4e86\uff1f", "cid": 193063847, "dimension": {"width": 1920, "height": 1080, "rotate": 0}, "short_link_v2": "https://b23.tv/BV19z411q7Go", "bvid": "BV19z411q7Go", "season_type": 0, "is_ogv": false, "ogv_info": null, "enable_vt": 0, "ai_rcmd": null, "rcmd_reason": "\u606d\u559c\u606d\u559c\uff01\uff01"}, {"aid": 498190316, "videos": 1, "tid": 171, "tname": "\u7535\u5b50\u7ade\u6280", "copyright": 1, "pic": "http://i1.hdslb.com/bfs/archive/10425256a96c107ba11a00559652a81f5492adb2.jpg", "title": "\u3010 \u5439  \u725b \u3011", "pubdate": 1589960649, "ctime": 1589960649, "desc": "\u6c42\u5173\u6ce8\u3002\u6c42\u5173\u6ce8\u3002\u6c42\u5173\u6ce8\u3002\u6c42\u5173\u6ce8\u3002\u6c42\u5173\u6ce8\u3002\u6c42\u5173\u6ce8\u3002\u6c42\u5173\u6ce8\u3002\u6c42\u5173\u6ce8\u3002\u6c42\u5173\u6ce8\u3002\u6c42\u5173\u6ce8\u3002\u6c42\u5173\u6ce8\u3002\u6c42\u5173\u6ce8\u3002\u6c42\u5173\u6ce8\u3002\u6c42\u5173\u6ce8\u3002\u6c42\u5173\u6ce8\u3002\u6c42\u5173\u6ce8\u3002\u6c42\u5173\u6ce8\u3002\u6c42\u5173\u6ce8\u3002\u6c42\u5173\u6ce8\u3002\u6c42\u5173\u6ce8\u3002\u6c42\u5173\u6ce8\u3002\u6c42\u5173\u6ce8\u3002", "state": 0, "duration": 522, "mission_id": 13195, "rights": {"bp": 0, "elec": 0, "download": 0, "movie": 0, "pay": 0, "hd5": 1, "no_reprint": 1, "autoplay": 1, "ugc_pay": 0, "is_cooperation": 0, "ugc_pay_preview": 0, "no_background": 0, "arc_pay": 0, "pay_free_watch": 0}, "owner": {"mid": 13118294, "name": "\u8d85\u7ea7\u795e\u5947\u7684\u6728\u5076", "face": "https://i2.hdslb.com/bfs/face/eef8f10a4d8761fb3175445a78799576cb12999f.jpg"}, "stat": {"aid": 498190316, "view": 4620134, "danmaku": 17435, "reply": 4384, "favorite": 28935, "coin": 45122, "share": 7658, "now_rank": 0, "his_rank": 11, "like": 255672, "dislike": 0, "vt": 0, "vv": 4620134}, "dynamic": "\u80fd\u86505\u4e2a\u804c\u4e1a\u7684\u6700\u5f3a\u73a9\u5bb6\uff1a\u6ca1\u6709\u4e4b\u4e00\uff01\u6ca1\u6709\u4e4b\u4e00\uff01\u6ca1\u6709\u4e4b\u4e00\uff01\u6ca1\u6709\u4e4b\u4e00\uff01\u6ca1\u6709\u4e4b\u4e00\uff01\u6ca1\u6709\u4e4b\u4e00\uff01\n#\u624b\u6e38\u4f5c\u4e1a-\u641e\u7b11\u5a31\u4e50##\u738b\u8005\u8363\u8000##\u7535\u5b50\u7ade\u6280#", "cid": 193164863, "dimension": {"width": 1920, "height": 1080, "rotate": 0}, "short_link_v2": "https://b23.tv/BV1BK411W77D", "bvid": "BV1BK411W77D", "season_type": 0, "is_ogv": false, "ogv_info": null, "enable_vt": 0, "ai_rcmd": null, "rcmd_reason": "\u7cbe\u7b80\u7248\u7f51\u7edc\u723d\u6587"}, {"aid": 413203229, "videos": 1, "tid": 257, "tname": "\u914d\u97f3", "copyright": 1, "pic": "http://i1.hdslb.com/bfs/archive/784c7e937cba1fa029bb80bf6fa88beec951a492.jpg", "title": "\u3010\u6731\u4e9a\u6587\u3011\u4e00\u65b9\u901a\u884c\u6765\u4e86\uff01\u8fd8\u8ddf\u65e0\u60e8\u7834\u65f6\u7a7abattle\uff01#\u752d\u6b63\u9762#05", "pubdate": 1590034899, "ctime": 1590034899, "desc": "\u8fd9\u6b21\u5e26\u6765\u4e00\u65b9\u901a\u884c\u548c\u65e0\u60e8\u5927\u4eba\u5173\u4e8e\u7231\u7684\u54f2\u5b66battle\uff01\u7b2c\u4e00\u6b21\u73a9\u539f\u521b\u53f0\u8bcd\u914d\u97f3\uff0c\u5404\u4f4d\u591a\u591a\u5305\u6db5\uff01", "state": 0, "duration": 289, "rights": {"bp": 0, "elec": 0, "download": 0, "movie": 0, "pay": 0, "hd5": 1, "no_reprint": 1, "autoplay": 1, "ugc_pay": 0, "is_cooperation": 0, "ugc_pay_preview": 0, "no_background": 0, "arc_pay": 0, "pay_free_watch": 0}, "owner": {"mid": 545482920, "name": "\u6731\u4e9a\u6587", "face": "http://i0.hdslb.com/bfs/face/e5189c426407cbb83a9d7eb573bffb901cd81488.jpg"}, "stat": {"aid": 413203229, "view": 1178096, "danmaku": 8104, "reply": 4406, "favorite": 14093, "coin": 47756, "share": 3945, "now_rank": 0, "his_rank": 40, "like": 116337, "dislike": 0, "vt": 0, "vv": 1178096}, "dynamic": "#\u914d\u97f3##\u6731\u4e9a\u6587##\u752d\u6b63\u9762#\u4f60\u4eec\u60f3\u542c\u7684\u4e00\u65b9\u5927\u7237\u548c\u65e0\u60e8\u5927\u4eba\u4e00\u6b21\u6027\u5b89\u6392\u4e0a\u4e86\uff01521\u73a9\u70b9\u513f\u4e0d\u4e00\u6837\uff0c\u7b2c\u4e00\u6b21\u5c1d\u8bd5\u539f\u521b\u53f0\u8bcd\u914d\u97f3\uff0c\u6765\u542c\u4e24\u5927\u53cd\u6d3e\u8de8\u65f6\u7a7abattle\u7231\u7684\u54f2\u5b66\uff01", "cid": 193467673, "dimension": {"width": 1920, "height": 1080, "rotate": 0}, "short_link_v2": "https://b23.tv/BV1RV411k7Rs", "pub_location": "\u5317\u4eac", "bvid": "BV1RV411k7Rs", "season_type": 0, "is_ogv": false, "ogv_info": null, "enable_vt": 0, "ai_rcmd": null, "rcmd_reason": "\u539f\u521b\u53f0\u8bcd\u914d\u97f3\uff0c\u592a\u7edd\u4e86"}, {"aid": 583179250, "videos": 1, "tid": 230, "tname": "\u8f6f\u4ef6\u5e94\u7528", "copyright": 1, "pic": "http://i2.hdslb.com/bfs/archive/c07e74cb4d92cfd3422a07246516b9e559e7cbc3.jpg", "title": "\u827a\u672f\u5bb6\u4eec\u79c1\u7528\u768410\u6b3e\u5168\u7f51\u6700\u9ad8\u903c\u683c\u63d0\u9ad8\u5ba1\u7f8eAPP \u6444\u5f71\u8bbe\u8ba1\u7f8e\u672f\u827a\u672f", "pubdate": 1589634042, "ctime": 1589560175, "desc": "\u5168\u7f51\u7b2c\u4e00\u5ba1\u7f8e\u8282\u76ee \u2192 BV1KJ411e7nN\n01 DAZED\n02 Pinterest\n03\u56fd\u5bb6\u5730\u7406\u202804 PANTONE\n05 iMuseum\n06 VART\n07\u30c1\u30e9\u30b7\u30df\u30e5\u30fc\u30b8\u30a2\u30e0\n08 www.shashasha.co/en\n09 https://moom.cat/tw\n10 POSING APP", "state": 0, "duration": 627, "mission_id": 13313, "rights": {"bp": 0, "elec": 0, "download": 0, "movie": 0, "pay": 0, "hd5": 0, "no_reprint": 1, "autoplay": 1, "ugc_pay": 0, "is_cooperation": 0, "ugc_pay_preview": 0, "no_background": 0, "arc_pay": 0, "pay_free_watch": 0}, "owner": {"mid": 19526512, "name": "TenGuSan", "face": "https://i1.hdslb.com/bfs/face/7ae4916301a78744c54dfb30a0ab260aff57458f.jpg"}, "stat": {"aid": 583179250, "view": 1500639, "danmaku": 5950, "reply": 1746, "favorite": 176583, "coin": 91571, "share": 9981, "now_rank": 0, "his_rank": 5, "like": 114307, "dislike": 0, "vt": 0, "vv": 1500639}, "dynamic": "#2020\u8111\u6d1e\u8282 \u795e\u5947\u8111\u56de\u8def\u5927\u8d4f##\u9ed1\u79d1\u6280##APP\u63a8\u8350#\u827a\u672f\u5bb6\u4eec\u79c1\u7528\u768410\u6b3e\u5168\u7f51\u6700\u9ad8\u903c\u683c\u6444\u5f71 \u8bbe\u8ba1 \u827a\u672fAPP", "cid": 191443920, "dimension": {"width": 1920, "height": 1080, "rotate": 0}, "short_link_v2": "https://b23.tv/BV1uz4y1d7zx", "bvid": "BV1uz4y1d7zx", "season_type": 0, "is_ogv": false, "ogv_info": null, "enable_vt": 0, "ai_rcmd": null, "rcmd_reason": "\u592a\u8bb2\u7a76\u4e86\uff0c\u5e72\u8d27\u6ee1\u6ee1\uff01"}, {"aid": 583208249, "videos": 1, "tid": 24, "tname": "MAD\u00b7AMV", "copyright": 1, "pic": "http://i1.hdslb.com/bfs/archive/0fddf0868020135b93dc7efe95135bb3d77288f0.jpg", "title": "\u66fe\u706b\u7206\u5168\u7f51\u7684\u300aFalling Again\u300b\uff0c\u4f60\u662f\u5426\u8fd8\u77e5\u9053\uff1f", "pubdate": 1589463035, "ctime": 1589436267, "desc": "BGM:Falling Again\n\u6807\u9898\u6807\u51c6\u683c\u5f0f\uff0c\u6b22\u8fce\u5410\u69fd", "state": 0, "duration": 161, "mission_id": 13382, "rights": {"bp": 0, "elec": 0, "download": 0, "movie": 0, "pay": 0, "hd5": 1, "no_reprint": 1, "autoplay": 1, "ugc_pay": 0, "is_cooperation": 0, "ugc_pay_preview": 0, "no_background": 0, "arc_pay": 0, "pay_free_watch": 0}, "owner": {"mid": 3834994, "name": "-\u7cbd\u5b50\u9171-", "face": "https://i1.hdslb.com/bfs/face/6ae5c446c3fda259c44e3c8b527cbf14a4917cf7.jpg"}, "stat": {"aid": 583208249, "view": 9086193, "danmaku": 13362, "reply": 4045, "favorite": 299095, "coin": 254187, "share": 22653, "now_rank": 0, "his_rank": 3, "like": 422923, "dislike": 0, "vt": 0, "vv": 9086193}, "dynamic": "#\u5168\u80fd\u6253\u5361\u6311\u6218##AMV##MAD.AMV#", "cid": 190843183, "dimension": {"width": 1920, "height": 1080, "rotate": 0}, "short_link_v2": "https://b23.tv/BV17z4y1d72b", "bvid": "BV17z4y1d72b", "season_type": 0, "is_ogv": false, "ogv_info": null, "enable_vt": 0, "ai_rcmd": null, "rcmd_reason": "\u6ca1\u6709\u672a\u6765\u7684\u672a\u6765\u4e0d\u662f\u6211\u60f3\u8981\u7684\u672a\u6765"}, {"aid": 795748722, "videos": 1, "tid": 124, "tname": "\u793e\u79d1\u00b7\u6cd5\u5f8b\u00b7\u5fc3\u7406", "copyright": 1, "pic": "http://i2.hdslb.com/bfs/archive/f76c51b6fc5a55753f2c5de4631503a2af798f8e.jpg", "title": "\u3010\u4e3e\u4eba\u3011\u5982\u4f55\u6446\u8131\u201c\u95f4\u6b47\u6027\u8e0c\u8e87\u6ee1\u5fd7\uff0c\u957f\u671f\u6027\u6df7\u5403\u7b49\u6b7b\u201d \uff1f", "pubdate": 1589886084, "ctime": 1589886084, "desc": "\u89c6\u9891\uff1a\n\u7761\u7720\u662f\u4f60\u7684\u8d85\u80fd\u529b BV1uC4y1s75D\n\u80a2\u4f53\u8bed\u8a00\u5851\u9020\u4f60\u81ea\u5df1 BV1ZJ411W7tJ\n\u5982\u4f55\u638c\u63a7\u4f60\u81ea\u5df1\u7684\u81ea\u7531\u65f6\u95f4 BV1VE41147R3\nThomas Frank\u4e60\u60ef\u8ffd\u8e2a\u517b\u6210\u6cd5 BV1k7411a7Ey\n\u5728\u95f2\u6687\u65f6\u95f4\u91cc\u5982\u4f55\u5173\u6389\u4e0e\u5de5\u4f5c\u76f8\u5173\u7684\u60f3\u6cd5 BV1c7411p7sE\n\u54c8\u4f5b\u5e78\u798f\u8bfe BV1kx411S7ZU\n\u5982\u4f55\u6210\u4e3a\u4e00\u4e2a\u66f4\u597d\u7684\u4ea4\u8c08\u8005 BV1zK41157gA", "state": 0, "duration": 1068, "mission_id": 13338, "rights": {"bp": 0, "elec": 0, "download": 0, "movie": 0, "pay": 0, "hd5": 1, "no_reprint": 1, "autoplay": 1, "ugc_pay": 0, "is_cooperation": 0, "ugc_pay_preview": 0, "no_background": 0, "arc_pay": 0, "pay_free_watch": 0}, "owner": {"mid": 9303228, "name": "\u6c5f\u6e56\u4e3e\u4eba", "face": "https://i0.hdslb.com/bfs/face/2006645655466f897a9f43a184cccabcfd006de4.jpg"}, "stat": {"aid": 795748722, "view": 882770, "danmaku": 8193, "reply": 1228, "favorite": 80827, "coin": 61113, "share": 8537, "now_rank": 0, "his_rank": 6, "like": 71186, "dislike": 0, "vt": 0, "vv": 882770}, "dynamic": "#\u8bfb\u4e66##\u4eba\u6587##\u8da3\u5473\u79d1\u666e\u4eba\u6587#\n\u8fd9\u4efd\u201c\u8ff7\u832b\u8005\u4e66\u5355\u201d\uff0c\u5b83\u5c06\u4ece\u8eab\u4f53\u72b6\u6001\uff0c\u601d\u7ef4\u65b9\u5f0f\uff0c\u65f6\u95f4\u7ba1\u7406\uff0c\u60c5\u7eea\u7ba1\u7406\uff0c\u6c9f\u901a\u6280\u5de7\u4e94\u4e2a\u65b9\u9762\u529b\u56fe\u53bb\u5e2e\u52a9\u4f60\uff0c\u91cd\u65b0\u627e\u56de\u5bf9\u751f\u6d3b\u7684\u638c\u63a7\u611f\u3002\u4e0d\u8fc7\u91cd\u70b9\u8fd8\u662f\u662f\u4f60\u600e\u4e48\u505a\uff0c\u4e16\u754c\u4e0a\u6700\u611a\u8822\u7684\u884c\u4e3a\uff0c\u83ab\u8fc7\u4e8e\u4e00\u76f4\u91cd\u590d\u76f8\u540c\u4e8b\u60c5\uff0c\u5374\u671f\u5f85\u4e0d\u540c\u7684\u7ed3\u679c\u3002", "cid": 193076239, "dimension": {"width": 1920, "height": 1080, "rotate": 0}, "short_link_v2": "https://b23.tv/BV1GC4y1p7wH", "bvid": "BV1GC4y1p7wH", "season_type": 0, "is_ogv": false, "ogv_info": null, "enable_vt": 0, "ai_rcmd": null, "rcmd_reason": "\u8eab\u4f53\u662f\u9769\u547d\u7684\u672c\u94b1"}, {"aid": 840652081, "videos": 1, "tid": 130, "tname": "\u97f3\u4e50\u7efc\u5408", "copyright": 2, "pic": "http://i2.hdslb.com/bfs/archive/b24a8d230fec855f2794140d803cb4c6e9c84c7a.jpg", "title": "\u71c3\u7206\u5168\u573a\uff01LiSA\u9996\u5531\u300a\u9b3c\u706d\u4e4b\u5203\u300b\u6700\u71c3\u795e\u66f2\u300a\u7d05\u84ee\u83ef\u300b\u5b8c\u6574\u7248~\u3010\u6700\u9ad8\u97f3\u753b\u8d28\u6536\u85cf\u3011\u3010\u8001\u7ec7\u9996\u6b21\u73b0\u573a\u6fc0\u60c5\u6f14\u5531\u52a8\u6f2b\u6b4c\u66f2\u300a\u7d05\u84ee\u83ef\u300b\u5b8c\u6574\u7248\u3011", "pubdate": 1589415234, "ctime": 1589415234, "desc": "\u7528BD\u84dd\u5149\u6e90\u538b\u5236\u3002LiSA\u9996\u6b21\u73b0\u573a\u6f14\u5531\u7684\u300a\u9b3c\u706d\u4e4b\u5203\u300b\u795e\u66f2\u300a\u7d05\u84ee\u83ef\u300b\u5b8c\u6574\u7248\u57281\u4e073\u5343\u4eba\u516c\u6f14\u4e0a\u3002\n\n\u65e5\u672c\u52a8\u6f2b2019\u5e74\u6700\u91cd\u5927\u4e8b\u4ef6\u5c31\u662f\u91cd\u65b0\u53d1\u73b0\u4e86\u300a\u9b3c\u706d\u4e4b\u5203\u300b\uff01\u8fd9\u90e82016\u5e74\u6f2b\u753b\u5f00\u59cb\u8fde\u8f7d\u65f6\u58f0\u54cd\u4e0d\u5927\u7684\u52a8\u6f2b\u57282019\u5e74\u52a8\u753b\u5f00\u64ad\u540e\u6c14\u52bf\u5982\u8679\u521b\u9020\u4e86\u5947\u8ff9\uff0c\u8dc3\u5347\u4e3a\u9876\u7ea7\u52a8\u6f2b\u3002\u4e0d\u4ec5\u52a8\u753b\u4ee5\u78be\u538b\u4e4b\u52bf\u79f0\u9738\uff0c\u5176\u6f2b\u753b2019\u5e74\u9500\u91cf\u4e5f\u4ee51080\u4e07\u518c\u7d27\u7d27\u8feb\u8fd1\u300a\u6d77\u8d3c\u738b\u300b\uff08\u96c6\u82f1\u793e\u6570\u636e\uff09\uff0c\u800cORICON\u65e5\u672c\u516c\u4fe1\u699c\u6570\u636e\u66f4\u662f\u4ee51205.7\u4e07\u518c\u7ec8\u7ed3\u4e86\u300a\u6d77\u8d3c\u738b\u300b\u6f2b\u753b\u9500\u91cf13\u5e74\u8fde\u51a0\u3002LiSA\u5531\u7684\u5176OP\u795e\u66f2\u300a\u7d05\u84ee\u83ef\u300b\u5df2\u7ecf\u6210\u4e3a\u52a8\u6f2b\u70ed\u8840\u71c3\u66f2\u65b0\u6807\u6746\uff01", "state": 0, "duration": 297, "rights": {"bp": 0, "elec": 0, "download": 0, "movie": 0, "pay": 0, "hd5": 1, "no_reprint": 0, "autoplay": 1, "ugc_pay": 0, "is_cooperation": 0, "ugc_pay_preview": 0, "no_background": 0, "arc_pay": 0, "pay_free_watch": 0}, "owner": {"mid": 322032202, "name": "\u70bd\u590f\u591c\u4e4b\u5fc3", "face": "http://i1.hdslb.com/bfs/face/092e4110fa7d0a1e1c07bb45855e48be8f3f000b.jpg"}, "stat": {"aid": 840652081, "view": 34371910, "danmaku": 64300, "reply": 16568, "favorite": 984422, "coin": 505169, "share": 166777, "now_rank": 0, "his_rank": 6, "like": 1414607, "dislike": 0, "vt": 0, "vv": 34371910}, "dynamic": "#\u97f3\u4e50\u73b0\u573a##\u7ec7\u90e8\u91cc\u6c99##LiSA##\u7d05\u84ee\u83ef##\u7ea2\u83b2\u534e##\u9b3c\u706d\u4e4b\u5203##\u52a8\u6f2b\u6b4c\u66f2##\u52a8\u6f2b\u97f3\u4e50#\n\u71c3\u7206\u5168\u573a\uff01LiSA\u9996\u5531\u300a\u9b3c\u706d\u4e4b\u5203\u300b\u6700\u71c3\u795e\u66f2\u300a\u7d05\u84ee\u83ef\u300b\u5b8c\u6574\u7248~", "cid": 190752469, "dimension": {"width": 1920, "height": 1080, "rotate": 0}, "short_link_v2": "https://b23.tv/BV1B54y1X7Ls", "bvid": "BV1B54y1X7Ls", "season_type": 0, "is_ogv": false, "ogv_info": null, "enable_vt": 0, "ai_rcmd": null, "rcmd_reason": "\u73b0\u573a\u4e5f\u8fd9\u4e48\u7a33\uff0c\u592a\u5f3a\u4e86\uff01"}, {"aid": 668236102, "videos": 1, "tid": 193, "tname": "MV", "copyright": 1, "pic": "http://i2.hdslb.com/bfs/archive/9be0743038783bff21ebdf5c20671ed7b8ef5e03.jpg", "title": "\u795e\u66f2\u5929\u540e\u9f9a\u7433\u5a1c\u7684\u300a\u4e0b\u5c71\u300b\u6765\u4e86\uff01\u4e00\u4ebahold\u516d\u58f0\u90e8\uff0c\u56fd\u5bb6\u961f\u795e\u4ed9\u6f14\u7ece", "pubdate": 1589533249, "ctime": 1589533276, "desc": "\u9f9a\u6c0f\u5531\u6cd5 \u4e0b\u5c71\u800c\u6765 \u4e28\u300a\u68a6\u5e7b\u897f\u6e38\u300b\u7535\u8111\u7248 x \u9f9a\u7433\u5a1c\u4e28\u65b9\u5bf8\u5c71\u95e8\u6d3e\u66f2\u300a\u4e0b\u5c71\u300b\n\u9f9a\u8001\u5e08\u5de6\u624b\u79bb\u9b42 \u53f3\u624b\u50ac\u7720~\n\u8fd8\u4e0d\u5feb\u5feb\u6253\u4e0a\u4e34\u65f6\u7b26\uff0c\u5e26\u597d\u9ad8\u54c1\u836f\uff0c\u62c9\u4e0a\u7075\u5203\u5ba0\uff0c\u8ddf\u7740\u9f9a\u8001\u5e08\u4e00\u8d77\u300a\u4e0b\u5c71\u300b\u95ef\u4e09\u754c\u3002\n5\u670815\u65e5, \u65b9\u5bf8\u5c71\u4e0b\uff0c\u5c11\u4fa0\u4eec\u4e0d\u89c1\u4e0d\u6563\uff01\nPS\uff1a\u5343\u53e4\u4e4b\u8c1c\uff0c\u5c0f\u843d\u5230\u5e95\u662f\u8c01#55\n\u4f5c\u8bcd\uff1a\u6731\u658c\u8bed \u7c73\u5361\u517d\n\u4f5c\u66f2\uff1a\u6731\u658c\u8bed\n\u539f\u5531\uff1a\u8981\u4e0d\u8981\u4e70\u83dc", "state": 0, "duration": 184, "rights": {"bp": 0, "elec": 0, "download": 0, "movie": 0, "pay": 0, "hd5": 1, "no_reprint": 1, "autoplay": 1, "ugc_pay": 0, "is_cooperation": 0, "ugc_pay_preview": 0, "no_background": 0, "arc_pay": 0, "pay_free_watch": 0}, "owner": {"mid": 444935584, "name": "\u68a6\u5e7b\u897f\u6e38\u7535\u8111\u7248", "face": "https://i1.hdslb.com/bfs/face/dd54aff29caac79baa10b18892e61ae9aabf7ce9.jpg"}, "stat": {"aid": 668236102, "view": 12237469, "danmaku": 33238, "reply": 12412, "favorite": 287379, "coin": 321381, "share": 69467, "now_rank": 0, "his_rank": 5, "like": 605113, "dislike": 0, "vt": 0, "vv": 12237469}, "dynamic": "#\u9f9a\u73b2\u5a1c##\u4e0b\u5c71##\u68a6\u5e7b\u897f\u6e38\u7535\u8111\u7248#", "cid": 191168255, "dimension": {"width": 1920, "height": 1080, "rotate": 0}, "short_link_v2": "https://b23.tv/BV1Ha4y1e71f", "bvid": "BV1Ha4y1e71f", "season_type": 0, "is_ogv": false, "ogv_info": null, "enable_vt": 0, "ai_rcmd": null, "rcmd_reason": "\u8fd9\u54ea\u662f\u4e0b\u5c71\uff0c\u8fd9\u662f\u795e\u4ed9\u4e0b\u51e1"}, {"aid": 200650394, "videos": 2, "tid": 28, "tname": "\u539f\u521b\u97f3\u4e50", "copyright": 1, "pic": "http://i0.hdslb.com/bfs/archive/14133161e306b17ad1d84c60bb0a3da4eb9b0dd7.jpg", "title": "\u3010\u67d0\u5e7b/\u4e2d\u56fdBOY\u3011\u7535\u5b50\u7f8a", "pubdate": 1589515250, "ctime": 1589514368, "desc": "\u300a\u7535\u5b50\u7f8a\u300b\n\u7f16\u66f2\uff1a\u4e2d\u56fdboy\n\u4f5c\u8bcd/\u4f5c\u66f2/\u6f14\u5531\uff1a\u67d0\u5e7b\n\u6df7\u97f3\uff1a\u6768\u79cb\u5112\nMV\uff1a\u85e4\u4e95\u65cb\u98ce\n\u63d2\u753b\uff1a\u602a\u751f\u97f3", "state": 0, "duration": 674, "mission_id": 13312, "rights": {"bp": 0, "elec": 0, "download": 0, "movie": 0, "pay": 0, "hd5": 0, "no_reprint": 1, "autoplay": 1, "ugc_pay": 0, "is_cooperation": 0, "ugc_pay_preview": 0, "no_background": 0, "arc_pay": 0, "pay_free_watch": 0}, "owner": {"mid": 1577804, "name": "\u67d0\u5e7b\u541b", "face": "https://i2.hdslb.com/bfs/face/a7eda2f97431d13f89a43b310262d1b19be83c01.jpg"}, "stat": {"aid": 200650394, "view": 15422591, "danmaku": 97860, "reply": 23139, "favorite": 421697, "coin": 715389, "share": 87869, "now_rank": 0, "his_rank": 1, "like": 833323, "dislike": 0, "vt": 0, "vv": 15422591}, "dynamic": "\u6211\uff0c\u67d0\u5e7b\uff0c\u63a5\u53d7\u4f60\u4e2d\u56fdboy\u7684\u6311\u6218", "cid": 191608695, "dimension": {"width": 1920, "height": 1080, "rotate": 0}, "short_link_v2": "https://b23.tv/BV1Bz411q7p7", "bvid": "BV1Bz411q7p7", "season_type": 0, "is_ogv": false, "ogv_info": null, "enable_vt": 0, "ai_rcmd": null, "rcmd_reason": "\u4eff\u751f\u4eba\u4f1a\u68a6\u89c1\u7535\u5b50\u7f8a\u5417\uff1f"}, {"aid": 583231938, "videos": 1, "tid": 47, "tname": "\u77ed\u7247\u00b7\u624b\u4e66", "copyright": 1, "pic": "http://i2.hdslb.com/bfs/archive/bc43fd87b0ab9f29acea212d2b869635532739c5.jpg", "title": "\u3010JOJO/\u8352\u6728\u5e84\u3011\u731b\u7537\u7248\u65b0\u5b9d\u5c9b\u5b8c\u6574\u7248", "pubdate": 1589587206, "ctime": 1589587235, "desc": "\u7ec8\u4e8e\u5b8c\u6210\u4e86\uff01\u53bb\u5e748\u6708\u4efd\u5f00\u4e86\u8fd9\u4e2a\u5751\uff0c\u5de5\u7a0b\u91cf\u4e4b\u5927\u662f\u6211\u4e07\u4e07\u6ca1\u60f3\u5230\u7684\uff0c\u5728\u5927\u5b66\u65f6\u4e5f\u6bd4\u8f83\u5fd9\uff0c\u6bcf\u5929\u90fd\u575a\u6301\u81f3\u5c11\u753b\u4e00\u5f20\uff0c\u672c\u6765\u8fd1900\u5f20\u539f\u753b\uff0c\u6211\u8fd8\u662f\u5728\u89c6\u9891\u540e\u9762\u51cf\u5e27\u518d\u52a0PR\u8865\u5e27\u6765\u51cf\u5c11\u5de5\u4f5c\u91cf\uff0c\u4e0d\u7136\u662f\u660e\u5e74\u90fd\u89c1\u4e0d\u5230\u5b8c\u6574\u7248\u4e86\uff0c\u6211\u4e5f\u8017\u4e0d\u5230\u660e\u5e74\u4e86\uff0c\u505a\u8fd9\u4e2a\u89c6\u9891\u771f\u7684\u5f88\u8003\u9a8c\u8010\u6027\u3002\u7b97\u662f\u4e3a\u4e86\u7ed9\u7c89\u4e1d\u4e00\u4e2a\u4ea4\u4ee3\u5427\uff0c\u903c\u7740\u81ea\u5df1\u505a\u5b8c\u4e86\u8fd9\u4e2a\u89c6\u9891\uff08\u5176\u5b9e\u662f\u771f\u7684\u60f3\u9e3d\uff09\u3002", "state": 0, "duration": 94, "rights": {"bp": 0, "elec": 0, "download": 0, "movie": 0, "pay": 0, "hd5": 0, "no_reprint": 1, "autoplay": 0, "ugc_pay": 0, "is_cooperation": 0, "ugc_pay_preview": 0, "no_background": 0, "arc_pay": 0, "pay_free_watch": 0}, "owner": {"mid": 12364896, "name": "XXM\u52a8\u753b", "face": "https://i0.hdslb.com/bfs/face/8330ed10285141e5d28e82c5a92b6800de9b7854.jpg"}, "stat": {"aid": 583231938, "view": 3310272, "danmaku": 7374, "reply": 2898, "favorite": 141705, "coin": 183876, "share": 28869, "now_rank": 0, "his_rank": 13, "like": 294687, "dislike": 0, "vt": 0, "vv": 3310272}, "dynamic": "#\u65b0\u5b9d\u5cf6##\u731b\u7537\u7248##JOJO#", "cid": 191552475, "dimension": {"width": 1920, "height": 1080, "rotate": 0}, "short_link_v2": "https://b23.tv/BV1Lz4y1d7vx", "pub_location": "\u798f\u5efa", "bvid": "BV1Lz4y1d7vx", "season_type": 0, "is_ogv": false, "ogv_info": null, "enable_vt": 0, "ai_rcmd": null, "rcmd_reason": "\u90aa\u6076\u7ec4\u7ec7\u70ed\u821e\u73b0\u573a"}, {"aid": 753141008, "videos": 1, "tid": 21, "tname": "\u65e5\u5e38", "copyright": 1, "pic": "http://i2.hdslb.com/bfs/archive/de7b2326b1cf94bd6e2da1cc48707be2d95feed3.jpg", "title": "\u8857\u8bbf\u7f8e\u56fd\u7ebd\u7ea6\u8def\u4eba\uff0c\u7279\u6717\u666e\u6297\u75ab\u505a\u7684\u600e\u4e48\u6837\uff1f", "pubdate": 1589773092, "ctime": 1589773092, "desc": "", "state": 0, "duration": 338, "mission_id": 13259, "rights": {"bp": 0, "elec": 0, "download": 0, "movie": 0, "pay": 0, "hd5": 1, "no_reprint": 1, "autoplay": 1, "ugc_pay": 0, "is_cooperation": 0, "ugc_pay_preview": 0, "no_background": 0, "arc_pay": 0, "pay_free_watch": 0}, "owner": {"mid": 176037767, "name": "\u6211\u662f\u90ed\u6770\u745e", "face": "http://i2.hdslb.com/bfs/face/6182455e4d61159121c223ddc7a3a381f2d4d056.jpg"}, "stat": {"aid": 753141008, "view": 3385196, "danmaku": 24494, "reply": 7679, "favorite": 14606, "coin": 66892, "share": 8436, "now_rank": 0, "his_rank": 2, "like": 251667, "dislike": 0, "vt": 0, "vv": 3385196}, "dynamic": "", "cid": 192351160, "dimension": {"width": 1920, "height": 1080, "rotate": 0}, "short_link_v2": "https://b23.tv/BV13k4y167u2", "bvid": "BV13k4y167u2", "season_type": 0, "is_ogv": false, "ogv_info": null, "enable_vt": 0, "ai_rcmd": null, "rcmd_reason": "\u6bcf\u4e2a\u56fd\u5bb6\u90fd\u6709\u6e05\u9192\u7684\u4eba\u548c\u8ff7\u7cca\u7684\u4eba"}, {"aid": 455703929, "videos": 1, "tid": 212, "tname": "\u7f8e\u98df\u4fa6\u63a2", "copyright": 1, "pic": "http://i2.hdslb.com/bfs/archive/9893febe5d2896088b11a2dc8df39186be0b4d97.jpg", "title": "Up\u4e3b\u5386\u65f630\u5929\uff0c\u7ec8\u6781\u8fd8\u539fKFC\u5ae9\u725b\u4e94\u65b9\uff01\uff01\uff01", "pubdate": 1589799263, "ctime": 1589799263, "desc": "\u5982\u679c\u4f60\u559c\u6b22\u6211\u7684\u89c6\u9891\uff0c\u8bf7\u5e2e\u6211\u70b9\u4e2a\u8d5e\u3001\u6295\u4e2a\u5e01\u3001\u8c22\u8c22\u5927\u5bb6\uff01\uff01\uff01\n\u4e5f\u53ef\u4ee5\u6536\u85cf\u4e00\u6ce2\u3001\u4ee5\u5907\u4e0d\u65f6\u4e4b\u9700", "state": 0, "duration": 445, "mission_id": 13239, "rights": {"bp": 0, "elec": 0, "download": 0, "movie": 0, "pay": 0, "hd5": 0, "no_reprint": 1, "autoplay": 1, "ugc_pay": 0, "is_cooperation": 0, "ugc_pay_preview": 0, "no_background": 0, "arc_pay": 0, "pay_free_watch": 0}, "owner": {"mid": 270105105, "name": "\u8d56\u76ae\u7334\u7231\u7f8e\u98df", "face": "https://i0.hdslb.com/bfs/face/fa7a39f18a4f89c48a37dc06bd450dac77b7242d.jpg"}, "stat": {"aid": 455703929, "view": 2765466, "danmaku": 17938, "reply": 4060, "favorite": 103855, "coin": 173133, "share": 21797, "now_rank": 0, "his_rank": 3, "like": 248609, "dislike": 0, "vt": 0, "vv": 2765466}, "dynamic": "\u8c28\u4ee5\u6b64\u7247\u732e\u7ed9\u540c\u6837\u6000\u6709\u5ae9\u725b\u4e94\u65b9\u60c5\u6000\u7684\u4f60\uff01\uff01\uff01\n#\u5ae9\u725b\u4e94\u65b9##KFC##\u80af\u5fb7\u57fa#", "cid": 192489458, "dimension": {"width": 1920, "height": 1080, "rotate": 0}, "short_link_v2": "https://b23.tv/BV1p5411s7fF", "bvid": "BV1p5411s7fF", "season_type": 0, "is_ogv": false, "ogv_info": null, "enable_vt": 0, "ai_rcmd": null, "rcmd_reason": "KFC:\u5ae9\u725b\u4e94\u65b9 \u7334\u54e5:\u5ae9\u7287\u4e94\u65b9"}, {"aid": 668197945, "videos": 1, "tid": 138, "tname": "\u641e\u7b11", "copyright": 1, "pic": "http://i0.hdslb.com/bfs/archive/c40f77f783a4ea7a1359e63724e28316bdcd0d3f.jpg", "title": "\u3010\u6731\u4e00\u65e6\u7684\u7834\u4ea7\u751f\u6d3b\u301101  \u7ec8\u4e8e\u53ef\u4ee5\u4f53\u9a8c\u4eba\u60c5\u51b7\u6696\u4e86", "pubdate": 1589717164, "ctime": 1589717164, "desc": "\u516c\u4f17\u53f7\uff1a\u6731\u4e00\u65e6\u7684\u67af\u71e5\u751f\u6d3b\n\u5fae\u535a@\u6731\u4e00\u65e6\u7684\u67af\u71e5\u751f\u6d3b\nYouTube  \u3010\u6731\u4e00\u65e6\u7684\u67af\u71e5\u751f\u6d3b\u3011\u5b98\u65b9\u9891\u9053\n\u7f51\u6613\u4e91/\u77e5\u4e4e\uff1a\u6731\u4e00\u65e6\u7684\u67af\u71e5\u751f\u6d3b", "state": 0, "duration": 209, "mission_id": 13399, "rights": {"bp": 0, "elec": 0, "download": 0, "movie": 0, "pay": 0, "hd5": 1, "no_reprint": 1, "autoplay": 1, "ugc_pay": 0, "is_cooperation": 0, "ugc_pay_preview": 0, "no_background": 0, "arc_pay": 0, "pay_free_watch": 0}, "owner": {"mid": 437316738, "name": "\u6731\u4e00\u65e6\u7684\u67af\u71e5\u751f\u6d3b", "face": "http://i0.hdslb.com/bfs/face/48ad92f9e0eb9516f491ed18457e2a73e865ea8c.jpg"}, "stat": {"aid": 668197945, "view": 3829873, "danmaku": 21912, "reply": 5474, "favorite": 5881, "coin": 14755, "share": 3722, "now_rank": 0, "his_rank": 30, "like": 181295, "dislike": 0, "vt": 0, "vv": 3829873}, "dynamic": "#\u641e\u7b11\u8868\u6f14# #\u9017\u6bd4# #\u6731\u4e00\u65e6#", "cid": 192160306, "dimension": {"width": 1080, "height": 1920, "rotate": 0}, "short_link_v2": "https://b23.tv/BV1Qa4y1i7Rj", "bvid": "BV1Qa4y1i7Rj", "season_type": 0, "is_ogv": false, "ogv_info": null, "enable_vt": 0, "ai_rcmd": null, "rcmd_reason": "\u53c8\u53cc\u53d2\u53d5\u7834\u4ea7\u4e86\uff1f"}, {"aid": 370679250, "videos": 1, "tid": 138, "tname": "\u641e\u7b11", "copyright": 1, "pic": "http://i2.hdslb.com/bfs/archive/104c9805eec1dea8dff96ee5db46a9fc81ac8f2b.jpg", "title": "\u4e00\u8d77\u201c\u9020\u9020\u9020\u201d \uff081\uff09", "pubdate": 1589642311, "ctime": 1589642311, "desc": "\u8fd9\u51e0\u5929\u66f4\u65b0 \u4f60\u4eec\u60f3\u770b\u7684 \u4e0d\u8981\u201c\u505a\u201d\u6311\u6218\uff1f\uff01\n\uff08\u5c0f\u780d\u7b49\u642c\u8fc7\u6765\u65b0\u5de5\u4f5c\u5ba4\u624d\u80fd\u66f4\u65b0\u8c0b\u6743\u7be1\u4f4d4\uff09\n\n\u5e0c\u671b\u89c2\u4f17\u8001\u7237\u559c\u6b22\u8fd9\u4e2a\u7cfb\u5217\uff01\n\u7d20\u8d28\u4e09\u8fde\uff0c\u521b\u4f5c\u4e0d\u6613\uff0c\u5e0c\u671b\u4f60\u559c\u6b22\uff01", "state": 0, "duration": 448, "mission_id": 13398, "rights": {"bp": 0, "elec": 0, "download": 0, "movie": 0, "pay": 0, "hd5": 0, "no_reprint": 1, "autoplay": 1, "ugc_pay": 0, "is_cooperation": 0, "ugc_pay_preview": 0, "no_background": 0, "arc_pay": 0, "pay_free_watch": 0}, "owner": {"mid": 5970160, "name": "\u5c0f\u6f6e\u9662\u957f", "face": "https://i1.hdslb.com/bfs/face/834eb0de8d2f470bf03e4ea92831b14f3824c863.jpg"}, "stat": {"aid": 370679250, "view": 12100329, "danmaku": 73156, "reply": 10074, "favorite": 82448, "coin": 205279, "share": 28856, "now_rank": 0, "his_rank": 3, "like": 682362, "dislike": 0, "vt": 0, "vv": 12100329}, "dynamic": "\u6574\u65b0\u6d3b\uff01\u4e00\u8d77\u201c\u9020\u9020\u9020\u201d\uff01\uff1f\n\u5bb6\u5ead\u5c0f\u6e38\u620f\uff01\n\n\n#\u641e\u7b11##\u641e\u7b11\u6311\u6218##vlog#", "cid": 191817631, "dimension": {"width": 1920, "height": 1080, "rotate": 0}, "short_link_v2": "https://b23.tv/BV1nZ4y1p79e", "bvid": "BV1nZ4y1p79e", "season_type": 0, "is_ogv": false, "ogv_info": null, "enable_vt": 0, "ai_rcmd": null, "rcmd_reason": "\u6765\u554a~ \u9020\u4f5c\u554a~ \u53cd\u6b63\u6709\uff0c\u5927\u628a\u65f6\u5149~"}, {"aid": 883152322, "videos": 1, "tid": 201, "tname": "\u79d1\u5b66\u79d1\u666e", "copyright": 1, "pic": "http://i1.hdslb.com/bfs/archive/e1610c09954873ec8dd122fb83c2ea1c725048f8.jpg", "title": "\u9009\u773c\u955c\u6846\u6709\u4e2a\u516c\u5f0f\u4f60\u77e5\u9053\u5417\uff1f", "pubdate": 1589795931, "ctime": 1589795931, "desc": "-", "state": 0, "duration": 258, "mission_id": 13338, "rights": {"bp": 0, "elec": 0, "download": 0, "movie": 0, "pay": 0, "hd5": 0, "no_reprint": 1, "autoplay": 1, "ugc_pay": 0, "is_cooperation": 0, "ugc_pay_preview": 0, "no_background": 0, "arc_pay": 0, "pay_free_watch": 0}, "owner": {"mid": 95348560, "name": "\u9a6c\u8001\u5e08\u89c6\u5149\u5de5\u4f5c\u5ba4", "face": "https://i1.hdslb.com/bfs/face/8fefac68df5a269466edded561e01049aaabc73d.jpg"}, "stat": {"aid": 883152322, "view": 5107516, "danmaku": 7626, "reply": 8892, "favorite": 218297, "coin": 101913, "share": 41364, "now_rank": 0, "his_rank": 1, "like": 282992, "dislike": 0, "vt": 0, "vv": 5107516}, "dynamic": "#\u77e5\u8bc6\u5206\u4eab\u5b98# #\u79d1\u5b66# #\u79d1\u666e#", "cid": 192445748, "dimension": {"width": 1280, "height": 720, "rotate": 0}, "short_link_v2": "https://b23.tv/BV1xK4y187qB", "bvid": "BV1xK4y187qB", "season_type": 0, "is_ogv": false, "ogv_info": null, "enable_vt": 0, "ai_rcmd": null, "rcmd_reason": "\u6234\u4e86\u8fd9\u4e48\u4e45\u773c\u955c\u624d\u77e5\u9053\u6709\u8fd9\u56de\u4e8b"}, {"aid": 413183268, "videos": 1, "tid": 21, "tname": "\u65e5\u5e38", "copyright": 1, "pic": "http://i0.hdslb.com/bfs/archive/d7d0ed20c04f94cf6f6f8d81cccd88650b680af7.jpg", "title": "\u5f53\u4ee3\u8fbe\u82ac\u5947\uff01", "pubdate": 1589515250, "ctime": 1589513408, "desc": "\u6211\u5c31\u662f\u7ed8\u753b\u5927\u5e08\uff01", "state": 0, "duration": 764, "order_id": 10021564, "rights": {"bp": 0, "elec": 0, "download": 0, "movie": 0, "pay": 0, "hd5": 0, "no_reprint": 1, "autoplay": 1, "ugc_pay": 0, "is_cooperation": 0, "ugc_pay_preview": 0, "no_background": 0, "arc_pay": 0, "pay_free_watch": 0}, "owner": {"mid": 546195, "name": "\u8001\u756a\u8304", "face": "http://i0.hdslb.com/bfs/face/bc5ca101313d4db223c395d64779e76eb3482d60.jpg"}, "stat": {"aid": 413183268, "view": 9647635, "danmaku": 112788, "reply": 12858, "favorite": 98006, "coin": 207600, "share": 31995, "now_rank": 0, "his_rank": 2, "like": 625795, "dislike": 0, "vt": 0, "vv": 9647635}, "dynamic": "\u7ed8\u753b\u5929\u624d\uff01", "cid": 191166469, "dimension": {"width": 1920, "height": 1080, "rotate": 0}, "short_link_v2": "https://b23.tv/BV1fV411k7T2", "bvid": "BV1fV411k7T2", "season_type": 0, "is_ogv": false, "ogv_info": null, "enable_vt": 0, "ai_rcmd": null, "rcmd_reason": "\u4f60\u8bf4\u6211\u753b\uff0c\u5168\u573a\u6700\u4f73\u662f\u6bcd\u54e5"}, {"aid": 328206986, "videos": 1, "tid": 21, "tname": "\u65e5\u5e38", "copyright": 1, "pic": "http://i1.hdslb.com/bfs/archive/859ee7c154f00abc06295be35570c1a6570f4ae5.jpg", "title": "\u4ea4\u5f80\u7684\u65e5\u672c\u5973\u53cb\uff0c\u7a81\u7136\u548c\u6211\u63d0\u51fa\u8fd9\u4e2a\u8981\u6c42\uff0c\u8fd8\u662f\u4ed6\u5988\u5988\u5efa\u8bae\u7684...\u4f60\u80fd\u63a5\u53d7\u5417\uff1f\u3010\u6bd2\u8bc4\u8bba\u6311\u6218\u3011", "pubdate": 1589970350, "ctime": 1589970351, "desc": "up\u4e3b\u63a8\u8350 \u2605\u2605\u2605\u2605\u2605\u2605\u2605\u2605\u2605\u2605\u2605\u2605\u2605\u2605\u2605\u2605\u2605\u2605   \n\n\u5077\u4e70\u5c0f\u25cb\u4e66\u88ab\u5973\u53cb\u53d1\u73b0\u4e86\uff1aav62649117  \n\u6211\u4eec\u65b0\u5bb6\uff1aav73738297  \n\u9ed1\u8863\u4eba\u5077\u5077\u6e9c\u8fdb\u623f\u95f4\uff1aav71525034  \n\u65e5\u672c\u5973\u751f\u771f\u7684\u5f00\u653e\u5417\uff1f\uff1aav69918318  \n\u5973\u88c5\uff1aav68933209  \n\u7528vr\u770b\u7247\u88ab\u5973\u53cb\u53d1\u73b0\u540e: av68153467  \n\u7ed9\u65e5\u672c\u5916\u5a46\u5c1d\u4e2d\u56fd\u7279\u4ea7\uff1aav66621433  \n\u6211\u5f53\u7238\u7238\u5566\uff1aav65477669", "state": 0, "duration": 678, "mission_id": 13497, "rights": {"bp": 0, "elec": 0, "download": 0, "movie": 0, "pay": 0, "hd5": 0, "no_reprint": 1, "autoplay": 1, "ugc_pay": 0, "is_cooperation": 0, "ugc_pay_preview": 0, "no_background": 0, "arc_pay": 0, "pay_free_watch": 0}, "owner": {"mid": 16853896, "name": "kei\u548cmarin", "face": "https://i1.hdslb.com/bfs/face/ec3456e625a0c9ab7064264e927e85fa05dfe9bd.jpg"}, "stat": {"aid": 328206986, "view": 3304278, "danmaku": 24180, "reply": 2370, "favorite": 17904, "coin": 80887, "share": 3341, "now_rank": 0, "his_rank": 12, "like": 180828, "dislike": 0, "vt": 0, "vv": 3304278}, "dynamic": "marin\u548c\u5979\u5988\u7ed9\u6211\u63d0\u4e86\u4e2a\u8981\u6c42\uff0c\u6211\u76f8\u4fe1\u662f\u7537\u4eba\u90fd\u4e0d\u4f1a\u540c\u610f\uff01", "cid": 193204854, "dimension": {"width": 1920, "height": 1080, "rotate": 0}, "short_link_v2": "https://b23.tv/BV1fA411i7sR", "bvid": "BV1fA411i7sR", "season_type": 0, "is_ogv": false, "ogv_info": null, "enable_vt": 0, "ai_rcmd": null, "rcmd_reason": "\u82b1\u5f0f\u5582\u72d7\u7cae"}, {"aid": 968168950, "videos": 1, "tid": 214, "tname": "\u7530\u56ed\u7f8e\u98df", "copyright": 1, "pic": "http://i2.hdslb.com/bfs/archive/8a9eda8100878f0739efae5f41e4dd5260f938c5.jpg", "title": "\u3010\u5c0f\u9ea6\u7684\u4e00\u751f\u3011\u4e00\u682a\u5c0f\u9ea6\uff0c\u53d8\u5316\u51fa\u624e\u6839\u5728\u6bcf\u4e2a\u4eba\u8bb0\u5fc6\u91cc\u7684\u5473\u9053", "pubdate": 1589894344, "ctime": 1589894345, "desc": "\u5c0f\u65f6\u5019\u6700\u671f\u5f85\u201c\u53ee\u53ee\u54d0\u201d\u6572\u9ebb\u7cd6\u7684\u58f0\u97f3\uff0c\n\u8bb0\u5fc6\u91cc\u7237\u7237\u603b\u81ea\u5df1\u53d1\u9ea6\u82bd\u71ac\u7cd6\u7ed9\u6211\u4eec\u626f\u9ea6\u82bd\u7cd6\n\u4ece\u4e00\u6367\u9ea6\u5b50\u5230\u4e00\u7b50\u9ea6\u5b50\uff0c\u4e0d\u8fc7\u662f\u751f\u547d\u7684\u8f6e\u56de\u3002\n\u9ea6\u82bd\u80fd\u71ac\u7cd6\uff0c\u9ea6\u79c6\u80fd\u7f16\u5e3d\uff0c\u9762\u7c89\u80fd\u505a\u5404\u79cd\u7f8e\u98df\n\u5305\u5b50 \u51c9\u76ae \u8089\u5939\u998d\uff0c\u9ebb\u82b1 \u9762\u6761 \u70e4\u9762\u7b4b\u2026\n\u5feb\u544a\u8bc9\u6211\u4f60\u6700\u559c\u6b22\u4ec0\u4e48\u9762\u98df\u5427\uff01", "state": 0, "duration": 1145, "mission_id": 13417, "rights": {"bp": 0, "elec": 0, "download": 0, "movie": 0, "pay": 0, "hd5": 0, "no_reprint": 1, "autoplay": 1, "ugc_pay": 0, "is_cooperation": 0, "ugc_pay_preview": 0, "no_background": 0, "arc_pay": 0, "pay_free_watch": 0}, "owner": {"mid": 19577966, "name": "\u674e\u5b50\u67d2", "face": "https://i2.hdslb.com/bfs/face/82d27965dae3b2fe9e52780c6309c7b37ad4cbf2.jpg"}, "stat": {"aid": 968168950, "view": 3408421, "danmaku": 42908, "reply": 9304, "favorite": 36660, "coin": 195508, "share": 19736, "now_rank": 0, "his_rank": 8, "like": 307404, "dislike": 0, "vt": 0, "vv": 3408421}, "dynamic": "\u4ece\u9ea6\u7c92\u5230\u98df\u7cae\uff0c\u505a\u82b1\u5f0f\u9762\u98df\uff0c\u56de\u987e\u5c0f\u9ea6\u7684\u4e00\u751f", "cid": 192881577, "dimension": {"width": 1920, "height": 1080, "rotate": 0}, "short_link_v2": "https://b23.tv/BV1ep4y1Q76i", "bvid": "BV1ep4y1Q76i", "season_type": 0, "is_ogv": false, "ogv_info": null, "enable_vt": 0, "ai_rcmd": null, "rcmd_reason": "\u7530\u5bb6\u5c11\u95f2\u6708\uff0c\u4e94\u6708\u4eba\u500d\u5fd9\u3002"}, {"aid": 668166801, "videos": 1, "tid": 182, "tname": "\u5f71\u89c6\u6742\u8c08", "copyright": 1, "pic": "http://i2.hdslb.com/bfs/archive/b83bac4ddc21b45efd5e1f5700d50f2a7abde5ce.jpg", "title": "\u7535\u5f71\u6700TOP 149\uff1a\u4e00\u53e3\u6c14\u770b\u5b8c\u300a\u52a0\u52d2\u6bd4\u6d77\u76d7\u300b\u7cfb\u52171\uff5e5\u90e8", "pubdate": 1590064805, "ctime": 1590064806, "desc": "\u672c\u671f\u54b1\u6765\u804a\u804a\u300a\u52a0\u52d2\u6bd4\u6d77\u76d7\u300b\u7cfb\u5217\u4e94\u90e8\u66f2\uff0c\u5ef6\u7ef514\u5e74\u7684\u5927\u7cfb\u5217\u4e00\u6b21\u6027\u809d\u5b8c\u3002", "state": 0, "duration": 5673, "rights": {"bp": 0, "elec": 0, "download": 0, "movie": 0, "pay": 0, "hd5": 1, "no_reprint": 1, "autoplay": 1, "ugc_pay": 0, "is_cooperation": 0, "ugc_pay_preview": 0, "no_background": 0, "arc_pay": 0, "pay_free_watch": 0}, "owner": {"mid": 17819768, "name": "\u7535\u5f71\u6700TOP", "face": "http://i2.hdslb.com/bfs/face/6b2ade215ea603b495648875c925172a863d16d4.jpg"}, "stat": {"aid": 668166801, "view": 6389102, "danmaku": 63505, "reply": 6626, "favorite": 120775, "coin": 311856, "share": 15119, "now_rank": 0, "his_rank": 4, "like": 329857, "dislike": 0, "vt": 0, "vv": 6389102}, "dynamic": "\u62fc\u4e86\uff01\u4e94\u90e8\u4e00\u6b21\u809d\u5b8c\uff01#\u52a0\u52d2\u6bd4\u6d77\u76d7##\u6770\u514b\u8239\u957f##\u7ea6\u7ff0\u5c3c\u5fb7\u666e#", "cid": 193491643, "dimension": {"width": 1920, "height": 1080, "rotate": 0}, "short_link_v2": "https://b23.tv/BV1ra4y1i7ZQ", "pub_location": "\u5c71\u4e1c", "bvid": "BV1ra4y1i7ZQ", "season_type": 0, "is_ogv": false, "ogv_info": null, "enable_vt": 0, "ai_rcmd": null, "rcmd_reason": "\u6d77\u4e0a\u4ea1\u7075\u5343\u5343\u4e07\uff0c\u6770\u514b\u8239\u957f\u60f9\u4e00\u534a"}]